{
 "0": {
  "bet-shaan": {
   "ims": {
    "Time": "2022-08-30T00:00:00Z",
    "Temp": 27.1,
    "RelHum": 88,
    "WindSpeed": 3,
    "WindDir": 304
   },
   "noaa": {
    "Time": "2022-08-30T00:00:00Z",
    "Pressure": [
     1000,
     975,
     950,
     925,
     900,
     850,
     800,
     750,
     700,
     650,
     600,
     550,
     500,
     450,
     400,
     350,
     300,
     250,
     200,
     150,
     100,
     70,
     50,
     30,
     20,
     10,
     7,
     5,
     3,
     2,
     1
    ],
    "Height": [
     282,
     1010,
     1758,
     2522,
     3313,
     4970,
     6715,
     8549,
     10475,
     12500,
     14642,
     16919,
     19386,
     22089,
     25045,
     28313,
     31975,
     36128,
     41023,
     47017,
     54986,
     61853,
     68517,
     79012,
     87611,
     102631,
     110580,
     118257,
     130524,
     140521,
     157883
    ],
    "Temp": [
     26,
     24,
     23,
     24,
     27,
     27,
     24,
     19,
     14,
     8,
     1,
     -3,
     -4,
     -8,
     -14,
     -21,
     -30,
     -40,
     -49,
     -62,
     -72,
     -71,
     -63,
     -54,
     -50,
     -43,
     -38,
     -31,
     -17,
     -16,
     -8
    ],
    "Dew": [
     22,
     21,
     21,
     15,
     5,
     2,
     -1,
     -5,
     -5,
     -7,
     -7,
     -16,
     -38,
     -37,
     -40,
     -42,
     -41,
     -56,
     -62,
     -74,
     -82,
     -84,
     -87,
     -90,
     -91,
     9999,
     9999,
     9999,
     9999,
     9999,
     9999
    ],
    "WindDir": [
     45,
     359,
     334,
     351,
     15,
     65,
     121,
     155,
     169,
     203,
     231,
     208,
     184,
     126,
     94,
     85,
     90,
     133,
     169,
     150,
     139,
     107,
     100,
     86,
     97,
     93,
     97,
     94,
     101,
     76,
     55
    ],
    "WindSpeed": [
     1,
     1,
     3,
     5,
     6,
     6,
     6,
     6,
     3,
     4,
     9,
     7,
     9,
     9,
     10,
     12,
     15,
     17,
     14,
     12,
     21,
     16,
     17,
     37,
     35,
     35,
     36,
     37,
     36,
     27,
     46
    ]
   },
   "uwyo": null
  },
  "megido": {
   "ims": {
    "Time": "2022-08-30T00:00:00Z",
    "Temp": 25.2,
    "RelHum": 100,
    "WindSpeed": 1.8,
    "WindDir": 274
   },
   "noaa": {
    "Time": "2022-08-30T00:00:00Z",
    "Pressure": [
     1000,
     975,
     950,
     925,
     900,
     850,
     800,
     750,
     700,
     650,
     600,
     550,
     500,
     450,
     400,
     350,
     300,
     250,
     200,
     150,
     100,
     70,
     50,
     30,
     20,
     10,
     7,
     5,
     3,
     2,
     1
    ],
    "Height": [
     269,
     1000,
     1748,
     2516,
     3310,
     4973,
     6719,
     8549,
     10475,
     12500,
     14642,
     16919,
     19386,
     22089,
     25049,
     28320,
     31978,
     36131,
     41023,
     47020,
     54996,
     61870,
     68540,
     79025,
     87624,
     102673,
     110616,
     118284,
     130528,
     140554,
     157916
    ],
    "Temp": [
     25,
     24,
     23,
     25,
     28,
     27,
     24,
     19,
     13,
     7,
     1,
     -3,
     -3,
     -8,
     -14,
     -21,
     -30,
     -40,
     -49,
     -62,
     -72,
     -70,
     -62,
     -55,
     -49,
     -43,
     -39,
     -31,
     -17,
     -15,
     -10
    ],
    "Dew": [
     22,
     22,
     20,
     13,
     3,
     0,
     -2,
     -3,
     -5,
     -6,
     -9,
     -19,
     -39,
     -36,
     -40,
     -43,
     -41,
     -54,
     -64,
     -74,
     -82,
     -85,
     -87,
     -91,
     -94,
     9999,
     9999,
     9999,
     9999,
     9999,
     9999
    ],
    "WindDir": [
     268,
     317,
     325,
     340,
     351,
     30,
     170,
     175,
     194,
     219,
     211,
     202,
     202,
     147,
     94,
     81,
     99,
     138,
     192,
     158,
     140,
     112,
     99,
     86,
     95,
     94,
     91,
     98,
     97,
     81,
     55
    ],
    "WindSpeed": [
     2,
     6,
     7,
     8,
     8,
     3,
     8,
     10,
     9,
     8,
     10,
     11,
     11,
     7,
     6,
     10,
     13,
     17,
     15,
     10,
     18,
     16,
     19,
     37,
     33,
     35,
     35,
     38,
     40,
     22,
     47
    ]
   },
   "uwyo": null
  },
  "sde-teiman": {
   "ims": {
    "Time": "2022-08-30T00:00:00Z",
    "Temp": 24.6,
    "RelHum": 93,
    "WindSpeed": 2.4,
    "WindDir": 326
   },
   "noaa": {
    "Time": "2022-08-30T00:00:00Z",
    "Pressure": [
     1000,
     975,
     950,
     925,
     900,
     850,
     800,
     750,
     700,
     650,
     600,
     550,
     500,
     450,
     400,
     350,
     300,
     250,
     200,
     150,
     100,
     70,
     50,
     30,
     20,
     10,
     7,
     5,
     3,
     2,
     1
    ],
    "Height": [
     275,
     1010,
     1758,
     2522,
     3316,
     4973,
     6715,
     8546,
     10469,
     12493,
     14635,
     16912,
     19383,
     22083,
     25039,
     28307,
     31965,
     36118,
     41017,
     47004,
     54980,
     61837,
     68487,
     78992,
     87582,
     102588,
     110547,
     118254,
     130495,
     140482,
     157851
    ],
    "Temp": [
     26,
     24,
     23,
     24,
     27,
     26,
     23,
     19,
     13,
     7,
     1,
     -3,
     -4,
     -8,
     -14,
     -21,
     -30,
     -40,
     -49,
     -62,
     -72,
     -72,
     -62,
     -54,
     -50,
     -43,
     -37,
     -30,
     -18,
     -16,
     -7
    ],
    "Dew": [
     22,
     22,
     20,
     12,
     5,
     5,
     0,
     -3,
     -5,
     -5,
     -6,
     -14,
     -40,
     -37,
     -39,
     -43,
     -41,
     -57,
     -63,
     -74,
     -81,
     -84,
     -88,
     -90,
     -91,
     9999,
     9999,
     9999,
     9999,
     9999,
     9999
    ],
    "WindDir": [
     350,
     351,
     0,
     15,
     20,
     80,
     128,
     134,
     138,
     158,
     200,
     209,
     162,
     130,
     102,
     87,
     87,
     121,
     166,
     131,
     138,
     102,
     98,
     89,
     96,
     92,
     101,
     99,
     97,
     69,
     58
    ],
    "WindSpeed": [
     5,
     6,
     6,
     7,
     7,
     4,
     7,
     10,
     8,
     6,
     8,
     11,
     11,
     12,
     12,
     14,
     19,
     18,
     16,
     14,
     23,
     17,
     19,
     36,
     38,
     38,
     36,
     33,
     37,
     26,
     42
    ]
   },
   "uwyo": null
  },
  "zefat": {
   "ims": {
    "Time": "2022-08-30T00:00:00Z",
    "Temp": 27.2,
    "RelHum": 30,
    "WindSpeed": 0.7,
    "WindDir": 348
   },
   "noaa": {
    "Time": "2022-08-30T00:00:00Z",
    "Pressure": [
     1000,
     975,
     950,
     925,
     900,
     850,
     800,
     750,
     700,
     650,
     600,
     550,
     500,
     450,
     400,
     350,
     300,
     250,
     200,
     150,
     100,
     70,
     50,
     30,
     20,
     10,
     7,
     5,
     3,
     2,
     1
    ],
    "Height": [
     262,
     984,
     1735,
     2509,
     3310,
     4977,
     6722,
     8553,
     10475,
     12500,
     14642,
     16916,
     19389,
     22096,
     25055,
     28326,
     31984,
     36138,
     41026,
     47027,
     55006,
     61886,
     68559,
     79055,
     87644,
     102713,
     110652,
     118303,
     130538,
     140557,
     158001
    ],
    "Temp": [
     29,
     28,
     27,
     28,
     30,
     28,
     24,
     19,
     13,
     8,
     1,
     -3,
     -3,
     -8,
     -14,
     -21,
     -30,
     -40,
     -49,
     -62,
     -72,
     -70,
     -62,
     -55,
     -50,
     -42,
     -40,
     -30,
     -18,
     -14,
     -10
    ],
    "Dew": [
     16,
     15,
     14,
     10,
     5,
     -2,
     -2,
     -3,
     -6,
     -9,
     -8,
     -21,
     -40,
     -36,
     -41,
     -43,
     -43,
     -51,
     -69,
     -74,
     -82,
     -84,
     -87,
     -91,
     -91,
     9999,
     9999,
     9999,
     9999,
     9999,
     9999
    ],
    "WindDir": [
     180,
     180,
     150,
     74,
     23,
     33,
     218,
     215,
     218,
     210,
     189,
     217,
     215,
     170,
     96,
     77,
     102,
     134,
     192,
     173,
     151,
     110,
     90,
     90,
     91,
     93,
     92,
     93,
     98,
     83,
     56
    ],
    "WindSpeed": [
     1,
     1,
     1,
     1,
     2,
     4,
     1,
     8,
     11,
     11,
     15,
     13,
     10,
     5,
     5,
     8,
     11,
     14,
     14,
     10,
     16,
     16,
     20,
     34,
     32,
     33,
     34,
     39,
     39,
     24,
     43
    ]
   },
   "uwyo": null
  }
 },
 "1": {
  "bet-shaan": {
   "ims": {
    "Time": "2022-08-30T01:00:00Z",
    "Temp": 27.4,
    "RelHum": 88,
    "WindSpeed": 2.8,
    "WindDir": 293
   },
   "noaa": {
    "Time": "2022-08-30T01:00:00Z",
    "Pressure": [
     1000,
     975,
     950,
     925,
     900,
     850,
     800,
     750,
     700,
     650,
     600,
     550,
     500,
     450,
     400,
     350,
     300,
     250,
     200,
     150,
     100,
     70,
     50,
     30,
     20,
     10,
     7,
     5,
     3,
     2,
     1
    ],
    "Height": [
     287,
     1016,
     1764,
     2528,
     3319,
     4976,
     6721,
     8554,
     10479,
     12503,
     14645,
     16922,
     19389,
     22090,
     25045,
     28313,
     31975,
     36130,
     41026,
     47019,
     54994,
     61859,
     68520,
     79018,
     87616,
     102657,
     110604,
     118288,
     130518,
     140478,
     157844
    ],
    "Temp": [
     26,
     24,
     23,
     24,
     27,
     27,
     24,
     19,
     14,
     8,
     1,
     -3,
     -4,
     -8,
     -14,
     -21,
     -30,
     -40,
     -49,
     -62,
     -72,
     -71,
     -63,
     -54,
     -50,
     -43,
     -38,
     -31,
     -18,
     -16,
     -8
    ],
    "Dew": [
     22,
     21,
     21,
     15,
     5,
     2,
     -1,
     -5,
     -5,
     -7,
     -7,
     -16,
     -38,
     -37,
     -40,
     -42,
     -43,
     -57,
     -62,
     -74,
     -82,
     -84,
     -87,
     -90,
     -91,
     9999,
     9999,
     9999,
     9999,
     9999,
     9999
    ],
    "WindDir": [
     92,
     355,
     336,
     298,
     26,
     77,
     126,
     155,
     168,
     196,
     228,
     208,
     177,
     124,
     94,
     88,
     94,
     138,
     168,
     149,
     140,
     106,
     98,
     90,
     96,
     96,
     95,
     92,
     103,
     76,
     62
    ],
    "WindSpeed": [
     1,
     1,
     3,
     5,
     6,
     6,
     7,
     7,
     4,
     4,
     9,
     7,
     9,
     10,
     11,
     13,
     16,
     17,
     14,
     12,
     21,
     17,
     18,
     37,
     36,
     35,
     36,
     38,
     34,
     27,
     44
    ]
   },
   "uwyo": null
  },
  "megido": {
   "ims": {
    "Time": "2022-08-30T01:00:00Z",
    "Temp": 25.3,
    "RelHum": 100,
    "WindSpeed": 1.6,
    "WindDir": 269
   },
   "noaa": {
    "Time": "2022-08-30T01:00:00Z",
    "Pressure": [
     1000,
     975,
     950,
     925,
     900,
     850,
     800,
     750,
     700,
     650,
     600,
     550,
     500,
     450,
     400,
     350,
     300,
     250,
     200,
     150,
     100,
     70,
     50,
     30,
     20,
     10,
     7,
     5,
     3,
     2,
     1
    ],
    "Height": [
     275,
     1007,
     1755,
     2523,
     3317,
     4979,
     6724,
     8554,
     10478,
     12503,
     14645,
     16922,
     19389,
     22091,
     25050,
     28321,
     31979,
     36132,
     41026,
     47022,
     55004,
     61876,
     68541,
     79032,
     87632,
     102695,
     110640,
     118315,
     130527,
     140512,
     157872
    ],
    "Temp": [
     25,
     24,
     23,
     25,
     28,
     27,
     24,
     19,
     13,
     7,
     1,
     -3,
     -3,
     -8,
     -14,
     -21,
     -30,
     -40,
     -49,
     -62,
     -72,
     -70,
     -62,
     -55,
     -49,
     -43,
     -39,
     -31,
     -18,
     -15,
     -10
    ],
    "Dew": [
     22,
     22,
     20,
     13,
     3,
     0,
     -2,
     -3,
     -5,
     -6,
     -9,
     -19,
     -39,
     -36,
     -40,
     -43,
     -41,
     -55,
     -64,
     -74,
     -82,
     -85,
     -87,
     -91,
     -94,
     9999,
     9999,
     9999,
     9999,
     9999,
     9999
    ],
    "WindDir": [
     278,
     320,
     328,
     284,
     302,
     47,
     170,
     175,
     190,
     213,
     211,
     205,
     194,
     143,
     95,
     86,
     102,
     143,
     189,
     158,
     140,
     111,
     98,
     91,
     94,
     97,
     90,
     95,
     100,
     79,
     62
    ],
    "WindSpeed": [
     2,
     6,
     7,
     8,
     8,
     3,
     8,
     10,
     9,
     8,
     10,
     11,
     11,
     8,
     7,
     10,
     14,
     17,
     15,
     10,
     18,
     16,
     20,
     36,
     34,
     35,
     35,
     38,
     37,
     23,
     45
    ]
   },
   "uwyo": null
  },
  "sde-teiman": {
   "ims": {
    "Time": "2022-08-30T01:00:00Z",
    "Temp": 24.4,
    "RelHum": 92,
    "WindSpeed": 1.7,
    "WindDir": 323
   },
   "noaa": {
    "Time": "2022-08-30T01:00:00Z",
    "Pressure": [
     1000,
     975,
     950,
     925,
     900,
     850,
     800,
     750,
     700,
     650,
     600,
     550,
     500,
     450,
     400,
     350,
     300,
     250,
     200,
     150,
     100,
     70,
     50,
     30,
     20,
     10,
     7,
     5,
     3,
     2,
     1
    ],
    "Height": [
     282,
     1017,
     1765,
     2529,
     3322,
     4978,
     6720,
     8551,
     10473,
     12497,
     14638,
     16915,
     19384,
     22083,
     25039,
     28307,
     31965,
     36120,
     41019,
     47008,
     54986,
     61842,
     68493,
     78997,
     87590,
     102615,
     110571,
     118282,
     130488,
     140442,
     157817
    ],
    "Temp": [
     26,
     24,
     23,
     24,
     27,
     26,
     23,
     19,
     13,
     7,
     1,
     -3,
     -4,
     -8,
     -14,
     -21,
     -30,
     -40,
     -49,
     -62,
     -72,
     -72,
     -62,
     -54,
     -50,
     -43,
     -37,
     -30,
     -19,
     -16,
     -7
    ],
    "Dew": [
     22,
     22,
     20,
     12,
     5,
     5,
     0,
     -3,
     -5,
     -5,
     -6,
     -14,
     -40,
     -37,
     -39,
     -43,
     -44,
     -58,
     -63,
     -74,
     -81,
     -84,
     -88,
     -90,
     -91,
     9999,
     9999,
     9999,
     9999,
     9999,
     9999
    ],
    "WindDir": [
     350,
     351,
     59,
     17,
     28,
     85,
     131,
     136,
     138,
     156,
     203,
     211,
     157,
     127,
     102,
     89,
     93,
     129,
     162,
     132,
     139,
     101,
     97,
     92,
     95,
     94,
     97,
     97,
     100,
     70,
     63
    ],
    "WindSpeed": [
     5,
     6,
     6,
     7,
     7,
     4,
     8,
     11,
     8,
     6,
     8,
     11,
     11,
     13,
     13,
     15,
     19,
     18,
     16,
     14,
     23,
     17,
     20,
     36,
     38,
     38,
     36,
     34,
     35,
     26,
     40
    ]
   },
   "uwyo": null
  },
  "zefat": {
   "ims": {
    "Time": "2022-08-30T01:00:00Z",
    "Temp": 26.8,
    "RelHum": 31,
    "WindSpeed": 1.2,
    "WindDir": 341
   },
   "noaa": {
    "Time": "2022-08-30T01:00:00Z",
    "Pressure": [
     1000,
     975,
     950,
     925,
     900,
     850,
     800,
     750,
     700,
     650,
     600,
     550,
     500,
     450,
     400,
     350,
     300,
     250,
     200,
     150,
     100,
     70,
     50,
     30,
     20,
     10,
     7,
     5,
     3,
     2,
     1
    ],
    "Height": [
     270,
     992,
     1744,
     2518,
     3318,
     4983,
     6727,
     8557,
     10479,
     12504,
     14645,
     16919,
     19393,
     22099,
     25056,
     28326,
     31985,
     36139,
     41029,
     47028,
     55015,
     61891,
     68561,
     79059,
     87654,
     102729,
     110677,
     118341,
     130540,
     140519,
     157936
    ],
    "Temp": [
     29,
     28,
     27,
     28,
     30,
     28,
     24,
     19,
     13,
     8,
     1,
     -3,
     -3,
     -8,
     -14,
     -21,
     -30,
     -40,
     -49,
     -62,
     -72,
     -70,
     -62,
     -55,
     -50,
     -42,
     -40,
     -30,
     -19,
     -14,
     -10
    ],
    "Dew": [
     16,
     15,
     14,
     10,
     5,
     -2,
     -2,
     -3,
     -6,
     -9,
     -8,
     -21,
     -40,
     -36,
     -41,
     -43,
     -43,
     -52,
     -68,
     -74,
     -82,
     -84,
     -87,
     -91,
     -91,
     9999,
     9999,
     9999,
     9999,
     9999,
     9999
    ],
    "WindDir": [
     173,
     173,
     148,
     76,
     34,
     46,
     204,
     205,
     213,
     210,
     196,
     222,
     208,
     165,
     98,
     83,
     105,
     139,
     192,
     171,
     151,
     109,
     90,
     93,
     91,
     96,
     91,
     92,
     99,
     80,
     63
    ],
    "WindSpeed": [
     1,
     1,
     1,
     1,
     2,
     5,
     2,
     8,
     11,
     11,
     14,
     13,
     10,
     6,
     5,
     8,
     12,
     14,
     14,
     10,
     15,
     16,
     21,
     34,
     32,
     34,
     34,
     39,
     37,
     24,
     42
    ]
   },
   "uwyo": null
  }
 },
 "10": {
  "bet-shaan": {
   "ims": {
    "Time": "2022-08-30T10:00:00Z",
    "Temp": 38.7,
    "RelHum": 34,
    "WindSpeed": 1.5,
    "WindDir": 335
   },
   "noaa": null,
   "uwyo": null
  },
  "megido": {
   "ims": {
    "Time": "2022-08-30T10:00:00Z",
    "Temp": 36.6,
    "RelHum": 42,
    "WindSpeed": 2.5,
    "WindDir": 296
   },
   "noaa": null,
   "uwyo": null
  },
  "sde-teiman": {
   "ims": {
    "Time": "2022-08-30T10:00:00Z",
    "Temp": 35.2,
    "RelHum": 41,
    "WindSpeed": 2.4,
    "WindDir": 306
   },
   "noaa": null,
   "uwyo": null
  },
  "zefat": {
   "ims": {
    "Time": "2022-08-30T10:00:00Z",
    "Temp": 31.4,
    "RelHum": 26,
    "WindSpeed": 2.2,
    "WindDir": 211
   },
   "noaa": null,
   "uwyo": null
  }
 },
 "11": {
  "bet-shaan": {
   "ims": {
    "Time": "2022-08-30T11:00:00Z",
    "Temp": 40.6,
    "RelHum": 30,
    "WindSpeed": 2.2,
    "WindDir": 322
   },
   "noaa": null,
   "uwyo": null
  },
  "megido": {
   "ims": {
    "Time": "2022-08-30T11:00:00Z",
    "Temp": 36.5,
    "RelHum": 43,
    "WindSpeed": 2.9,
    "WindDir": 302
   },
   "noaa": null,
   "uwyo": null
  },
  "sde-teiman": {
   "ims": {
    "Time": "2022-08-30T11:00:00Z",
    "Temp": 36.4,
    "RelHum": 41,
    "WindSpeed": 3.3,
    "WindDir": 317
   },
   "noaa": null,
   "uwyo": null
  },
  "zefat": {
   "ims": {
    "Time": "2022-08-30T11:00:00Z",
    "Temp": 32.2,
    "RelHum": 28,
    "WindSpeed": 1.2,
    "WindDir": 233
   },
   "noaa": null,
   "uwyo": null
  }
 },
 "2": {
  "bet-shaan": {
   "ims": {
    "Time": "2022-08-30T02:00:00Z",
    "Temp": 27.4,
    "RelHum": 87,
    "WindSpeed": 2.9,
    "WindDir": 297
   },
   "noaa": {
    "Time": "2022-08-30T02:00:00Z",
    "Pressure": [
     1000,
     975,
     950,
     925,
     900,
     850,
     800,
     750,
     700,
     650,
     600,
     550,
     500,
     450,
     400,
     350,
     300,
     250,
     200,
     150,
     100,
     70,
     50,
     30,
     20,
     10,
     7,
     5,
     3,
     2,
     1
    ],
    "Height": [
     292,
     1022,
     1771,
     2535,
     3326,
     4983,
     6727,
     8559,
     10483,
     12507,
     14648,
     16926,
     19392,
     22092,
     25046,
     28314,
     31974,
     36132,
     41029,
     47022,
     55003,
     61865,
     68524,
     79025,
     87622,
     102684,
     110629,
     118319,
     130512,
     140434,
     157804
    ],
    "Temp": [
     26,
     24,
     23,
     24,
     27,
     27,
     24,
     19,
     14,
     8,
     1,
     -3,
     -4,
     -8,
     -14,
     -21,
     -30,
     -40,
     -49,
     -62,
     -72,
     -71,
     -63,
     -54,
     -50,
     -43,
     -38,
     -31,
     -20,
     -16,
     -8
    ],
    "Dew": [
     22,
     21,
     21,
     15,
     5,
     2,
     -1,
     -5,
     -5,
     -7,
     -7,
     -17,
     -38,
     -37,
     -40,
     -42,
     -45,
     -58,
     -62,
     -74,
     -82,
     -84,
     -87,
     -90,
     -91,
     9999,
     9999,
     9999,
     9999,
     9999,
     9999
    ],
    "WindDir": [
     139,
     351,
     338,
     244,
     37,
     89,
     132,
     156,
     166,
     188,
     224,
     209,
     169,
     122,
     95,
     91,
     98,
     144,
     166,
     148,
     142,
     105,
     95,
     95,
     94,
     100,
     92,
     89,
     106,
     75,
     69
    ],
    "WindSpeed": [
     2,
     2,
     3,
     5,
     6,
     6,
     8,
     8,
     5,
     4,
     8,
     7,
     9,
     12,
     12,
     14,
     17,
     17,
     14,
     13,
     20,
     18,
     20,
     36,
     37,
     34,
     36,
     39,
     31,
     28,
     41
    ]
   },
   "uwyo": null
  },
  "megido": {
   "ims": {
    "Time": "2022-08-30T02:00:00Z",
    "Temp": 25.2,
    "RelHum": 100,
    "WindSpeed": 1.8,
    "WindDir": 268
   },
   "noaa": {
    "Time": "2022-08-30T02:00:00Z",
    "Pressure": [
     1000,
     975,
     950,
     925,
     900,
     850,
     800,
     750,
     700,
     650,
     600,
     550,
     500,
     450,
     400,
     350,
     300,
     250,
     200,
     150,
     100,
     70,
     50,
     30,
     20,
     10,
     7,
     5,
     3,
     2,
     1
    ],
    "Height": [
     281,
     1014,
     1763,
     2530,
     3324,
     4985,
     6729,
     8559,
     10482,
     12507,
     14648,
     16925,
     19392,
     22093,
     25051,
     28322,
     31980,
     36134,
     41029,
     47025,
     55013,
     61883,
     68543,
     79039,
     87640,
     102717,
     110665,
     118347,
     130526,
     140469,
     157827
    ],
    "Temp": [
     26,
     24,
     23,
     25,
     28,
     27,
     24,
     19,
     13,
     7,
     1,
     -3,
     -3,
     -8,
     -14,
     -21,
     -30,
     -40,
     -49,
     -62,
     -72,
     -70,
     -62,
     -55,
     -49,
     -43,
     -39,
     -31,
     -19,
     -16,
     -10
    ],
    "Dew": [
     22,
     22,
     20,
     14,
     4,
     0,
     -2,
     -3,
     -5,
     -6,
     -9,
     -19,
     -39,
     -36,
     -40,
     -43,
     -42,
     -56,
     -64,
     -74,
     -82,
     -85,
     -87,
     -91,
     -94,
     9999,
     9999,
     9999,
     9999,
     9999,
     9999
    ],
    "WindDir": [
     288,
     323,
     331,
     228,
     253,
     64,
     169,
     174,
     186,
     206,
     210,
     209,
     186,
     139,
     97,
     92,
     106,
     149,
     185,
     158,
     141,
     109,
     96,
     96,
     92,
     101,
     88,
     92,
     103,
     77,
     70
    ],
    "WindSpeed": [
     3,
     6,
     7,
     7,
     7,
     4,
     8,
     11,
     10,
     8,
     9,
     11,
     11,
     9,
     8,
     11,
     15,
     17,
     15,
     11,
     17,
     17,
     22,
     35,
     35,
     34,
     35,
     39,
     33,
     25,
     43
    ]
   },
   "uwyo": null
  },
  "sde-teiman": {
   "ims": {
    "Time": "2022-08-30T02:00:00Z",
    "Temp": 23.9,
    "RelHum": 94,
    "WindSpeed": 2.1,
    "WindDir": 326
   },
   "noaa": {
    "Time": "2022-08-30T02:00:00Z",
    "Pressure": [
     1000,
     975,
     950,
     925,
     900,
     850,
     800,
     750,
     700,
     650,
     600,
     550,
     500,
     450,
     400,
     350,
     300,
     250,
     200,
     150,
     100,
     70,
     50,
     30,
     20,
     10,
     7,
     5,
     3,
     2,
     1
    ],
    "Height": [
     289,
     1024,
     1772,
     2536,
     3328,
     4984,
     6725,
     8556,
     10477,
     12501,
     14642,
     16918,
     19386,
     22084,
     25039,
     28308,
     31965,
     36122,
     41022,
     47012,
     54992,
     61848,
     68500,
     79002,
     87599,
     102643,
     110596,
     118311,
     130481,
     140402,
     157782
    ],
    "Temp": [
     26,
     24,
     23,
     24,
     27,
     26,
     23,
     19,
     13,
     7,
     1,
     -3,
     -4,
     -8,
     -14,
     -21,
     -30,
     -40,
     -49,
     -62,
     -72,
     -72,
     -62,
     -54,
     -50,
     -43,
     -37,
     -30,
     -20,
     -16,
     -7
    ],
    "Dew": [
     22,
     22,
     20,
     13,
     5,
     5,
     -1,
     -3,
     -5,
     -5,
     -6,
     -15,
     -40,
     -37,
     -39,
     -43,
     -47,
     -59,
     -63,
     -74,
     -81,
     -84,
     -88,
     -90,
     -92,
     9999,
     9999,
     9999,
     9999,
     9999,
     9999
    ],
    "WindDir": [
     349,
     351,
     118,
     20,
     37,
     91,
     134,
     138,
     138,
     154,
     207,
     214,
     152,
     123,
     102,
     91,
     99,
     137,
     158,
     134,
     140,
     99,
     95,
     96,
     93,
     96,
     93,
     94,
     104,
     71,
     68
    ],
    "WindSpeed": [
     5,
     6,
     6,
     7,
     7,
     5,
     9,
     12,
     9,
     6,
     8,
     11,
     11,
     15,
     15,
     16,
     19,
     18,
     16,
     14,
     23,
     18,
     22,
     36,
     38,
     37,
     36,
     35,
     32,
     26,
     38
    ]
   },
   "uwyo": null
  },
  "zefat": {
   "ims": {
    "Time": "2022-08-30T02:00:00Z",
    "Temp": 26.7,
    "RelHum": 32,
    "WindSpeed": 0.8,
    "WindDir": 341
   },
   "noaa": {
    "Time": "2022-08-30T02:00:00Z",
    "Pressure": [
     1000,
     975,
     950,
     925,
     900,
     850,
     800,
     750,
     700,
     650,
     600,
     550,
     500,
     450,
     400,
     350,
     300,
     250,
     200,
     150,
     100,
     70,
     50,
     30,
     20,
     10,
     7,
     5,
     3,
     2,
     1
    ],
    "Height": [
     278,
     1000,
     1753,
     2527,
     3327,
     4990,
     6733,
     8562,
     10483,
     12508,
     14648,
     16923,
     19398,
     22102,
     25057,
     28327,
     31987,
     36141,
     41033,
     47030,
     55024,
     61896,
     68563,
     79063,
     87665,
     102745,
     110703,
     118379,
     130543,
     140480,
     157871
    ],
    "Temp": [
     29,
     28,
     27,
     28,
     29,
     28,
     24,
     19,
     13,
     8,
     1,
     -3,
     -3,
     -8,
     -14,
     -21,
     -30,
     -40,
     -49,
     -62,
     -72,
     -70,
     -62,
     -55,
     -50,
     -42,
     -39,
     -30,
     -20,
     -15,
     -9
    ],
    "Dew": [
     16,
     15,
     14,
     10,
     5,
     -1,
     -2,
     -3,
     -6,
     -9,
     -8,
     -20,
     -40,
     -36,
     -41,
     -43,
     -43,
     -54,
     -67,
     -74,
     -82,
     -84,
     -87,
     -91,
     -92,
     9999,
     9999,
     9999,
     9999,
     9999,
     9999
    ],
    "WindDir": [
     166,
     166,
     145,
     78,
     46,
     60,
     190,
     195,
     207,
     209,
     204,
     227,
     201,
     160,
     100,
     89,
     109,
     144,
     192,
     168,
     150,
     108,
     91,
     97,
     91,
     100,
     89,
     90,
     100,
     77,
     70
    ],
    "WindSpeed": [
     1,
     1,
     1,
     1,
     3,
     6,
     4,
     8,
     11,
     10,
     13,
     13,
     10,
     7,
     6,
     9,
     13,
     15,
     14,
     11,
     14,
     17,
     22,
     33,
     33,
     35,
     34,
     39,
     34,
     25,
     41
    ]
   },
   "uwyo": null
  }
 },
 "21": {
  "bet-shaan": {
   "ims": {
    "Time": "2022-08-29T21:00:00Z",
    "Temp": 28.8,
    "RelHum": 74,
    "WindSpeed": 3.5,
    "WindDir": 291
   },
   "noaa": {
    "Time": "2022-08-29T21:00:00Z",
    "Pressure": [
     1000,
     975,
     950,
     925,
     900,
     850,
     800,
     750,
     700,
     650,
     600,
     550,
     500,
     450,
     400,
     350,
     300,
     250,
     200,
     150,
     100,
     70,
     50,
     30,
     20,
     10,
     7,
     5,
     3,
     2,
     1
    ],
    "Height": [
     274,
     1007,
     1758,
     2530,
     3324,
     4993,
     6746,
     8580,
     10510,
     12537,
     14680,
     16964,
     19431,
     22135,
     25091,
     28363,
     32035,
     36196,
     41080,
     47078,
     55036,
     61918,
     68589,
     79089,
     87779,
     102814,
     110836,
     118555,
     130535,
     140705,
     158384
    ],
    "Temp": [
     27,
     26,
     24,
     26,
     28,
     28,
     24,
     19,
     14,
     8,
     2,
     -2,
     -4,
     -8,
     -15,
     -21,
     -29,
     -40,
     -50,
     -62,
     -73,
     -68,
     -63,
     -53,
     -49,
     -42,
     -36,
     -33,
     -19,
     -7,
     -6
    ],
    "Dew": [
     22,
     21,
     20,
     14,
     12,
     1,
     -3,
     -5,
     -6,
     -8,
     -10,
     -18,
     -40,
     -37,
     -38,
     -43,
     -42,
     -48,
     -70,
     -73,
     -81,
     -84,
     -87,
     -91,
     -94,
     9999,
     9999,
     9999,
     9999,
     9999,
     9999
    ],
    "WindDir": [
     405,
     356,
     359,
     353,
     414,
     21,
     168,
     150,
     132,
     107,
     119,
     177,
     170,
     143,
     117,
     46,
     78,
     83,
     134,
     155,
     140,
     102,
     108,
     96,
     79,
     93,
     93,
     91,
     73,
     116,
     107
    ],
    "WindSpeed": [
     5,
     6,
     7,
     8,
     8,
     2,
     6,
     7,
     6,
     6,
     8,
     8,
     10,
     9,
     6,
     7,
     10,
     12,
     14,
     11,
     22,
     20,
     29,
     35,
     30,
     42,
     38,
     38,
     44,
     17,
     15
    ]
   },
   "uwyo": null
  },
  "megido": {
   "ims": {
    "Time": "2022-08-29T21:00:00Z",
    "Temp": 26.2,
    "RelHum": 90,
    "WindSpeed": 1.9,
    "WindDir": 253
   },
   "noaa": {
    "Time": "2022-08-29T21:00:00Z",
    "Pressure": [
     1000,
     975,
     950,
     925,
     900,
     850,
     800,
     750,
     700,
     650,
     600,
     550,
     500,
     450,
     400,
     350,
     300,
     250,
     200,
     150,
     100,
     70,
     50,
     30,
     20,
     10,
     7,
     5,
     3,
     2,
     1
    ],
    "Height": [
     250,
     985,
     1745,
     2527,
     3333,
     4999,
     6749,
     8584,
     10510,
     12537,
     14680,
     16961,
     19431,
     22135,
     25091,
     28369,
     32038,
     36204,
     41080,
     47081,
     55042,
     61934,
     68600,
     79120,
     87800,
     102845,
     110849,
     118589,
     130566,
     140710,
     158367
    ],
    "Temp": [
     26,
     25,
     30,
     32,
     30,
     28,
     24,
     19,
     14,
     8,
     2,
     -2,
     -4,
     -8,
     -14,
     -20,
     -30,
     -40,
     -50,
     -62,
     -72,
     -69,
     -63,
     -53,
     -48,
     -42,
     -36,
     -31,
     -20,
     -7,
     -5
    ],
    "Dew": [
     23,
     21,
     9,
     4,
     4,
     3,
     -2,
     -4,
     -5,
     -6,
     -8,
     -18,
     -40,
     -37,
     -39,
     -44,
     -43,
     -47,
     -68,
     -74,
     -81,
     -84,
     -87,
     -91,
     -94,
     9999,
     9999,
     9999,
     9999,
     9999,
     9999
    ],
    "WindDir": [
     346,
     350,
     353,
     338,
     323,
     371,
     139,
     129,
     134,
     145,
     151,
     181,
     183,
     173,
     182,
     28,
     80,
     88,
     136,
     161,
     148,
     98,
     109,
     93,
     83,
     91,
     93,
     90,
     75,
     105,
     113
    ],
    "WindSpeed": [
     6,
     11,
     14,
     11,
     7,
     1,
     5,
     9,
     6,
     5,
     8,
     9,
     11,
     9,
     2,
     6,
     8,
     10,
     15,
     9,
     20,
     19,
     29,
     33,
     28,
     39,
     38,
     39,
     42,
     14,
     16
    ]
   },
   "uwyo": null
  },
  "sde-teiman": {
   "ims": {
    "Time": "2022-08-29T21:00:00Z",
    "Temp": 25.2,
    "RelHum": 93,
    "WindSpeed": 2.4,
    "WindDir": 301
   },
   "noaa": {
    "Time": "2022-08-29T21:00:00Z",
    "Pressure": [
     1000,
     975,
     950,
     925,
     900,
     850,
     800,
     750,
     700,
     650,
     600,
     550,
     500,
     450,
     400,
     350,
     300,
     250,
     200,
     150,
     100,
     70,
     50,
     30,
     20,
     10,
     7,
     5,
     3,
     2,
     1
    ],
    "Height": [
     278,
     1013,
     1761,
     2530,
     3324,
     4992,
     6746,
     8581,
     10506,
     12535,
     14677,
     16962,
     19428,
     22128,
     25084,
     28360,
     32025,
     36186,
     41077,
     47072,
     55018,
     61890,
     68567,
     79080,
     87746,
     102802,
     110796,
     118480,
     130533,
     140707,
     158386
    ],
    "Temp": [
     27,
     25,
     23,
     25,
     28,
     28,
     24,
     19,
     14,
     8,
     2,
     -3,
     -4,
     -8,
     -14,
     -21,
     -30,
     -40,
     -49,
     -63,
     -73,
     -69,
     -63,
     -54,
     -49,
     -42,
     -37,
     -33,
     -17,
     -8,
     -6
    ],
    "Dew": [
     22,
     21,
     20,
     13,
     9,
     3,
     -2,
     -4,
     -5,
     -5,
     -6,
     -15,
     -41,
     -37,
     -38,
     -41,
     -42,
     -50,
     -67,
     -70,
     -81,
     -85,
     -87,
     -90,
     -94,
     9999,
     9999,
     9999,
     9999,
     9999,
     9999
    ],
    "WindDir": [
     350,
     353,
     0,
     6,
     6,
     66,
     123,
     129,
     138,
     177,
     221,
     163,
     159,
     130,
     105,
     69,
     79,
     88,
     135,
     141,
     131,
     104,
     103,
     94,
     79,
     97,
     89,
     85,
     80,
     99,
     101
    ],
    "WindSpeed": [
     12,
     14,
     14,
     12,
     9,
     4,
     6,
     7,
     6,
     5,
     9,
     11,
     11,
     13,
     9,
     7,
     10,
     14,
     13,
     10,
     24,
     21,
     33,
     35,
     33,
     39,
     40,
     42,
     40,
     18,
     16
    ]
   },
   "uwyo": null
  },
  "zefat": {
   "ims": {
    "Time": "2022-08-29T21:00:00Z",
    "Temp": 29,
    "RelHum": 23,
    "WindSpeed": 1.5,
    "WindDir": 331
   },
   "noaa": {
    "Time": "2022-08-29T21:00:00Z",
    "Pressure": [
     1000,
     975,
     950,
     925,
     900,
     850,
     800,
     750,
     700,
     650,
     600,
     550,
     500,
     450,
     400,
     350,
     300,
     250,
     200,
     150,
     100,
     70,
     50,
     30,
     20,
     10,
     7,
     5,
     3,
     2,
     1
    ],
    "Height": [
     251,
     973,
     1735,
     2524,
     3333,
     5003,
     6752,
     8583,
     10510,
     12537,
     14680,
     16965,
     19431,
     22134,
     25093,
     28376,
     32045,
     36210,
     41087,
     47080,
     55056,
     61958,
     68620,
     79150,
     87815,
     102877,
     110866,
     118609,
     130637,
     140694,
     158353
    ],
    "Temp": [
     33,
     31,
     32,
     33,
     32,
     28,
     24,
     19,
     13,
     8,
     2,
     -2,
     -4,
     -8,
     -14,
     -20,
     -30,
     -40,
     -50,
     -62,
     -72,
     -69,
     -62,
     -53,
     -49,
     -43,
     -37,
     -31,
     -21,
     -9,
     -5
    ],
    "Dew": [
     15,
     14,
     10,
     3,
     1,
     -1,
     -3,
     -3,
     -5,
     -8,
     -12,
     -20,
     -40,
     -36,
     -41,
     -43,
     -43,
     -49,
     -67,
     -74,
     -81,
     -84,
     -87,
     -91,
     -94,
     9999,
     9999,
     9999,
     9999,
     9999,
     9999
    ],
    "WindDir": [
     349,
     349,
     355,
     371,
     368,
     325,
     236,
     285,
     372,
     368,
     180,
     179,
     198,
     205,
     280,
     -1,
     74,
     96,
     138,
     176,
     151,
     101,
     107,
     92,
     83,
     89,
     99,
     85,
     76,
     93,
     105
    ],
    "WindSpeed": [
     5,
     5,
     6,
     5,
     5,
     4,
     4,
     0,
     2,
     0,
     3,
     6,
     11,
     8,
     4,
     5,
     6,
     6,
     14,
     9,
     17,
     18,
     29,
     30,
     29,
     36,
     41,
     40,
     38,
     23,
     17
    ]
   },
   "uwyo": null
  }
 },
 "22": {
  "bet-shaan": {
   "ims": {
    "Time": "2022-08-29T22:00:00Z",
    "Temp": 28.2,
    "RelHum": 79,
    "WindSpeed": 3.4,
    "WindDir": 292
   },
   "noaa": {
    "Time": "2022-08-29T22:00:00Z",
    "Pressure": [
     1000,
     975,
     950,
     925,
     900,
     850,
     800,
     750,
     700,
     650,
     600,
     550,
     500,
     450,
     400,
     350,
     300,
     250,
     200,
     150,
     100,
     70,
     50,
     30,
     20,
     10,
     7,
     5,
     3,
     2,
     1
    ],
    "Height": [
     274,
     1007,
     1758,
     2530,
     3325,
     4994,
     6748,
     8582,
     10511,
     12539,
     14682,
     16966,
     19433,
     22137,
     25093,
     28365,
     32038,
     36200,
     41082,
     47081,
     55038,
     61921,
     68592,
     79092,
     87787,
     102822,
     110848,
     118569,
     130536,
     140714,
     158408
    ],
    "Temp": [
     27,
     26,
     24,
     26,
     28,
     28,
     24,
     19,
     14,
     8,
     2,
     -2,
     -4,
     -8,
     -15,
     -21,
     -29,
     -40,
     -50,
     -62,
     -73,
     -68,
     -63,
     -53,
     -49,
     -42,
     -36,
     -33,
     -19,
     -7,
     -6
    ],
    "Dew": [
     22,
     21,
     20,
     14,
     12,
     1,
     -3,
     -5,
     -6,
     -8,
     -10,
     -18,
     -40,
     -37,
     -38,
     -43,
     -42,
     -48,
     -70,
     -73,
     -81,
     -84,
     -87,
     -91,
     -94,
     9999,
     9999,
     9999,
     9999,
     9999,
     9999
    ],
    "WindDir": [
     422,
     356,
     360,
     353,
     433,
     19,
     171,
     149,
     130,
     102,
     114,
     175,
     170,
     144,
     118,
     44,
     77,
     81,
     133,
     156,
     140,
     101,
     108,
     97,
     78,
     93,
     93,
     91,
     72,
     118,
     110
    ],
    "WindSpeed": [
     5,
     7,
     7,
     8,
     8,
     2,
     6,
     7,
     6,
     6,
     8,
     8,
     10,
     9,
     6,
     6,
     9,
     11,
     14,
     11,
     22,
     20,
     30,
     35,
     29,
     42,
     38,
     38,
     44,
     16,
     13
    ]
   },
   "uwyo": null
  },
  "megido": {
   "ims": {
    "Time": "2022-08-29T22:00:00Z",
    "Temp": 25.8,
    "RelHum": 95,
    "WindSpeed": 2,
    "WindDir": 253
   },
   "noaa": {
    "Time": "2022-08-29T22:00:00Z",
    "Pressure": [
     1000,
     975,
     950,
     925,
     900,
     850,
     800,
     750,
     700,
     650,
     600,
     550,
     500,
     450,
     400,
     350,
     300,
     250,
     200,
     150,
     100,
     70,
     50,
     30,
     20,
     10,
     7,
     5,
     3,
     2,
     1
    ],
    "Height": [
     249,
     985,
     1745,
     2528,
     3334,
     5001,
     6750,
     8585,
     10511,
     12539,
     14682,
     16963,
     19433,
     22137,
     25093,
     28371,
     32041,
     36208,
     41082,
     47084,
     55044,
     61937,
     68603,
     79125,
     87808,
     102853,
     110860,
     118604,
     130568,
     140717,
     158389
    ],
    "Temp": [
     26,
     25,
     30,
     32,
     30,
     28,
     24,
     19,
     14,
     8,
     2,
     -2,
     -4,
     -8,
     -14,
     -20,
     -30,
     -40,
     -50,
     -62,
     -72,
     -69,
     -63,
     -53,
     -48,
     -42,
     -36,
     -31,
     -20,
     -7,
     -4
    ],
    "Dew": [
     23,
     21,
     8,
     4,
     4,
     3,
     -2,
     -4,
     -5,
     -6,
     -8,
     -18,
     -40,
     -37,
     -39,
     -44,
     -43,
     -47,
     -68,
     -74,
     -81,
     -84,
     -87,
     -91,
     -94,
     9999,
     9999,
     9999,
     9999,
     9999,
     9999
    ],
    "WindDir": [
     349,
     352,
     354,
     338,
     322,
     388,
     137,
     127,
     131,
     141,
     148,
     180,
     182,
     175,
     186,
     25,
     79,
     86,
     134,
     161,
     148,
     98,
     110,
     93,
     82,
     91,
     93,
     90,
     74,
     106,
     116
    ],
    "WindSpeed": [
     6,
     12,
     14,
     11,
     7,
     1,
     5,
     9,
     6,
     5,
     8,
     9,
     11,
     9,
     2,
     6,
     7,
     10,
     15,
     9,
     20,
     19,
     30,
     33,
     27,
     39,
     38,
     39,
     42,
     14,
     14
    ]
   },
   "uwyo": null
  },
  "sde-teiman": {
   "ims": {
    "Time": "2022-08-29T22:00:00Z",
    "Temp": 24.9,
    "RelHum": 93,
    "WindSpeed": 2.6,
    "WindDir": 311
   },
   "noaa": {
    "Time": "2022-08-29T22:00:00Z",
    "Pressure": [
     1000,
     975,
     950,
     925,
     900,
     850,
     800,
     750,
     700,
     650,
     600,
     550,
     500,
     450,
     400,
     350,
     300,
     250,
     200,
     150,
     100,
     70,
     50,
     30,
     20,
     10,
     7,
     5,
     3,
     2,
     1
    ],
    "Height": [
     278,
     1013,
     1761,
     2530,
     3324,
     4993,
     6748,
     8582,
     10508,
     12537,
     14679,
     16964,
     19430,
     22130,
     25086,
     28363,
     32028,
     36190,
     41080,
     47076,
     55020,
     61893,
     68571,
     79084,
     87754,
     102812,
     110808,
     118491,
     130535,
     140717,
     158412
    ],
    "Temp": [
     27,
     25,
     23,
     25,
     28,
     28,
     24,
     19,
     14,
     8,
     2,
     -3,
     -4,
     -8,
     -14,
     -21,
     -30,
     -40,
     -49,
     -63,
     -73,
     -69,
     -63,
     -54,
     -49,
     -42,
     -37,
     -33,
     -17,
     -8,
     -6
    ],
    "Dew": [
     22,
     21,
     20,
     13,
     9,
     3,
     -2,
     -4,
     -5,
     -5,
     -6,
     -15,
     -41,
     -37,
     -38,
     -41,
     -42,
     -50,
     -67,
     -70,
     -81,
     -85,
     -87,
     -90,
     -94,
     9999,
     9999,
     9999,
     9999,
     9999,
     9999
    ],
    "WindDir": [
     350,
     353,
     0,
     6,
     6,
     66,
     122,
     128,
     138,
     178,
     222,
     161,
     159,
     130,
     105,
     68,
     79,
     86,
     133,
     142,
     131,
     104,
     104,
     95,
     78,
     98,
     88,
     85,
     79,
     100,
     103
    ],
    "WindSpeed": [
     12,
     14,
     14,
     13,
     9,
     4,
     6,
     7,
     6,
     5,
     9,
     11,
     11,
     13,
     9,
     7,
     10,
     14,
     13,
     10,
     24,
     21,
     33,
     35,
     32,
     39,
     40,
     42,
     40,
     18,
     14
    ]
   },
   "uwyo": null
  },
  "zefat": {
   "ims": {
    "Time": "2022-08-29T22:00:00Z",
    "Temp": 28.8,
    "RelHum": 24,
    "WindSpeed": 0.9,
    "WindDir": 255
   },
   "noaa": {
    "Time": "2022-08-29T22:00:00Z",
    "Pressure": [
     1000,
     975,
     950,
     925,
     900,
     850,
     800,
     750,
     700,
     650,
     600,
     550,
     500,
     450,
     400,
     350,
     300,
     250,
     200,
     150,
     100,
     70,
     50,
     30,
     20,
     10,
     7,
     5,
     3,
     2,
     1
    ],
    "Height": [
     250,
     972,
     1735,
     2524,
     3334,
     5005,
     6753,
     8584,
     10511,
     12539,
     14682,
     16967,
     19433,
     22136,
     25095,
     28378,
     32048,
     36213,
     41090,
     47083,
     55058,
     61961,
     68623,
     79155,
     87823,
     102885,
     110876,
     118624,
     130641,
     140701,
     158370
    ],
    "Temp": [
     33,
     31,
     33,
     34,
     32,
     28,
     24,
     19,
     13,
     8,
     2,
     -2,
     -4,
     -8,
     -14,
     -20,
     -30,
     -40,
     -50,
     -62,
     -72,
     -69,
     -62,
     -53,
     -49,
     -43,
     -37,
     -31,
     -21,
     -8,
     -4
    ],
    "Dew": [
     15,
     14,
     10,
     3,
     1,
     -1,
     -3,
     -3,
     -5,
     -8,
     -12,
     -20,
     -40,
     -36,
     -41,
     -43,
     -43,
     -49,
     -67,
     -74,
     -81,
     -84,
     -87,
     -91,
     -94,
     9999,
     9999,
     9999,
     9999,
     9999,
     9999
    ],
    "WindDir": [
     357,
     357,
     365,
     385,
     384,
     339,
     237,
     288,
     379,
     376,
     180,
     177,
     197,
     206,
     289,
     -4,
     73,
     94,
     135,
     176,
     151,
     101,
     108,
     92,
     83,
     89,
     99,
     85,
     75,
     94,
     107
    ],
    "WindSpeed": [
     5,
     5,
     7,
     5,
     5,
     4,
     4,
     0,
     2,
     -1,
     2,
     6,
     11,
     8,
     4,
     5,
     5,
     6,
     14,
     9,
     17,
     18,
     29,
     30,
     29,
     36,
     41,
     40,
     38,
     23,
     15
    ]
   },
   "uwyo": null
  }
 },
 "23": {
  "bet-shaan": {
   "ims": {
    "Time": "2022-08-29T23:00:00Z",
    "Temp": 27.6,
    "RelHum": 84,
    "WindSpeed": 3.5,
    "WindDir": 301
   },
   "noaa": {
    "Time": "2022-08-29T23:00:00Z",
    "Pressure": [
     1000,
     975,
     950,
     925,
     900,
     850,
     800,
     750,
     700,
     650,
     600,
     550,
     500,
     450,
     400,
     350,
     300,
     250,
     200,
     150,
     100,
     70,
     50,
     30,
     20,
     10,
     7,
     5,
     3,
     2,
     1
    ],
    "Height": [
     274,
     1007,
     1758,
     2530,
     3325,
     4995,
     6749,
     8583,
     10513,
     12540,
     14684,
     16968,
     19435,
     22140,
     25096,
     28367,
     32041,
     36203,
     41085,
     47084,
     55040,
     61924,
     68596,
     79096,
     87795,
     102831,
     110861,
     118584,
     130536,
     140722,
     158432
    ],
    "Temp": [
     27,
     26,
     24,
     26,
     28,
     28,
     24,
     19,
     14,
     8,
     2,
     -2,
     -4,
     -8,
     -15,
     -21,
     -29,
     -40,
     -50,
     -62,
     -73,
     -68,
     -63,
     -53,
     -49,
     -42,
     -36,
     -33,
     -19,
     -6,
     -6
    ],
    "Dew": [
     22,
     21,
     20,
     14,
     12,
     1,
     -3,
     -5,
     -6,
     -8,
     -10,
     -18,
     -40,
     -37,
     -38,
     -43,
     -42,
     -48,
     -70,
     -73,
     -81,
     -84,
     -87,
     -91,
     -94,
     9999,
     9999,
     9999,
     9999,
     9999,
     9999
    ],
    "WindDir": [
     439,
     356,
     362,
     353,
     452,
     17,
     173,
     149,
     129,
     97,
     109,
     174,
     169,
     145,
     119,
     42,
     76,
     79,
     131,
     156,
     140,
     101,
     108,
     97,
     77,
     93,
     92,
     91,
     71,
     120,
     112
    ],
    "WindSpeed": [
     6,
     7,
     8,
     8,
     8,
     1,
     6,
     7,
     6,
     6,
     8,
     8,
     10,
     9,
     5,
     6,
     9,
     11,
     14,
     11,
     22,
     21,
     31,
     35,
     29,
     42,
     38,
     38,
     44,
     16,
     12
    ]
   },
   "uwyo": null
  },
  "megido": {
   "ims": {
    "Time": "2022-08-29T23:00:00Z",
    "Temp": 25.5,
    "RelHum": 97,
    "WindSpeed": 1.9,
    "WindDir": 268
   },
   "noaa": {
    "Time": "2022-08-29T23:00:00Z",
    "Pressure": [
     1000,
     975,
     950,
     925,
     900,
     850,
     800,
     750,
     700,
     650,
     600,
     550,
     500,
     450,
     400,
     350,
     300,
     250,
     200,
     150,
     100,
     70,
     50,
     30,
     20,
     10,
     7,
     5,
     3,
     2,
     1
    ],
    "Height": [
     248,
     984,
     1745,
     2528,
     3335,
     5002,
     6752,
     8587,
     10513,
     12540,
     14684,
     16965,
     19435,
     22140,
     25095,
     28373,
     32044,
     36211,
     41085,
     47087,
     55047,
     61940,
     68606,
     79129,
     87816,
     102862,
     110871,
     118618,
     130570,
     140725,
     158410
    ],
    "Temp": [
     26,
     25,
     30,
     32,
     30,
     28,
     24,
     19,
     14,
     8,
     2,
     -2,
     -4,
     -8,
     -14,
     -20,
     -30,
     -40,
     -50,
     -62,
     -72,
     -69,
     -63,
     -53,
     -48,
     -42,
     -36,
     -31,
     -20,
     -7,
     -4
    ],
    "Dew": [
     23,
     21,
     8,
     3,
     4,
     3,
     -2,
     -4,
     -5,
     -6,
     -8,
     -18,
     -40,
     -37,
     -39,
     -44,
     -43,
     -47,
     -69,
     -74,
     -81,
     -84,
     -87,
     -91,
     -94,
     9999,
     9999,
     9999,
     9999,
     9999,
     9999
    ],
    "WindDir": [
     353,
     354,
     355,
     338,
     321,
     404,
     136,
     124,
     128,
     138,
     145,
     179,
     181,
     176,
     191,
     23,
     78,
     84,
     131,
     161,
     148,
     97,
     110,
     93,
     81,
     91,
     93,
     90,
     73,
     107,
     118
    ],
    "WindSpeed": [
     7,
     12,
     14,
     11,
     7,
     1,
     5,
     9,
     6,
     5,
     8,
     9,
     11,
     9,
     1,
     5,
     7,
     10,
     15,
     9,
     20,
     19,
     30,
     32,
     27,
     40,
     38,
     39,
     42,
     14,
     13
    ]
   },
   "uwyo": null
  },
  "sde-teiman": {
   "ims": {
    "Time": "2022-08-29T23:00:00Z",
    "Temp": 24.9,
    "RelHum": 92,
    "WindSpeed": 2.5,
    "WindDir": 312
   },
   "noaa": {
    "Time": "2022-08-29T23:00:00Z",
    "Pressure": [
     1000,
     975,
     950,
     925,
     900,
     850,
     800,
     750,
     700,
     650,
     600,
     550,
     500,
     450,
     400,
     350,
     300,
     250,
     200,
     150,
     100,
     70,
     50,
     30,
     20,
     10,
     7,
     5,
     3,
     2,
     1
    ],
    "Height": [
     278,
     1013,
     1761,
     2530,
     3324,
     4994,
     6749,
     8584,
     10509,
     12539,
     14681,
     16966,
     19432,
     22132,
     25088,
     28365,
     32031,
     36193,
     41083,
     47079,
     55022,
     61895,
     68575,
     79089,
     87762,
     102823,
     110820,
     118501,
     130537,
     140728,
     158437
    ],
    "Temp": [
     27,
     25,
     23,
     25,
     28,
     28,
     24,
     19,
     14,
     8,
     2,
     -3,
     -4,
     -8,
     -14,
     -21,
     -30,
     -40,
     -49,
     -63,
     -73,
     -69,
     -63,
     -54,
     -49,
     -42,
     -37,
     -33,
     -17,
     -8,
     -6
    ],
    "Dew": [
     22,
     21,
     20,
     13,
     10,
     3,
     -2,
     -4,
     -5,
     -5,
     -6,
     -15,
     -41,
     -37,
     -38,
     -41,
     -42,
     -50,
     -68,
     -69,
     -81,
     -85,
     -87,
     -90,
     -94,
     9999,
     9999,
     9999,
     9999,
     9999,
     9999
    ],
    "WindDir": [
     350,
     353,
     0,
     5,
     5,
     65,
     122,
     128,
     138,
     179,
     223,
     158,
     159,
     130,
     105,
     67,
     79,
     84,
     132,
     142,
     131,
     104,
     104,
     95,
     77,
     98,
     87,
     84,
     78,
     102,
     105
    ],
    "WindSpeed": [
     12,
     14,
     14,
     13,
     9,
     4,
     6,
     7,
     6,
     5,
     9,
     11,
     11,
     13,
     9,
     7,
     9,
     13,
     13,
     9,
     24,
     22,
     34,
     35,
     32,
     39,
     41,
     43,
     40,
     18,
     13
    ]
   },
   "uwyo": null
  },
  "zefat": {
   "ims": {
    "Time": "2022-08-29T23:00:00Z",
    "Temp": 28.2,
    "RelHum": 27,
    "WindSpeed": 0.7,
    "WindDir": 233
   },
   "noaa": {
    "Time": "2022-08-29T23:00:00Z",
    "Pressure": [
     1000,
     975,
     950,
     925,
     900,
     850,
     800,
     750,
     700,
     650,
     600,
     550,
     500,
     450,
     400,
     350,
     300,
     250,
     200,
     150,
     100,
     70,
     50,
     30,
     20,
     10,
     7,
     5,
     3,
     2,
     1
    ],
    "Height": [
     250,
     972,
     1735,
     2525,
     3335,
     5006,
     6755,
     8586,
     10513,
     12540,
     14684,
     16969,
     19435,
     22138,
     25097,
     28380,
     32051,
     36217,
     41093,
     47085,
     55060,
     61965,
     68626,
     79159,
     87831,
     102893,
     110887,
     118639,
     130646,
     140707,
     158386
    ],
    "Temp": [
     34,
     31,
     33,
     34,
     32,
     28,
     24,
     19,
     13,
     8,
     2,
     -2,
     -4,
     -8,
     -14,
     -20,
     -30,
     -40,
     -50,
     -62,
     -72,
     -69,
     -62,
     -53,
     -49,
     -43,
     -37,
     -31,
     -21,
     -8,
     -4
    ],
    "Dew": [
     15,
     14,
     9,
     3,
     0,
     -1,
     -3,
     -3,
     -5,
     -8,
     -13,
     -20,
     -40,
     -36,
     -41,
     -43,
     -43,
     -49,
     -67,
     -74,
     -81,
     -84,
     -87,
     -91,
     -94,
     9999,
     9999,
     9999,
     9999,
     9999,
     9999
    ],
    "WindDir": [
     365,
     365,
     374,
     399,
     401,
     353,
     238,
     291,
     386,
     383,
     179,
     175,
     196,
     208,
     297,
     -8,
     72,
     92,
     132,
     176,
     151,
     100,
     109,
     92,
     83,
     88,
     99,
     85,
     74,
     94,
     109
    ],
    "WindSpeed": [
     6,
     6,
     7,
     6,
     5,
     4,
     4,
     0,
     1,
     -1,
     1,
     6,
     11,
     8,
     4,
     5,
     5,
     6,
     14,
     9,
     17,
     18,
     30,
     29,
     29,
     36,
     41,
     40,
     38,
     23,
     14
    ]
   },
   "uwyo": null
  }
 },
 "3": {
  "bet-shaan": {
   "ims": {
    "Time": "2022-08-30T03:00:00Z",
    "Temp": 27.4,
    "RelHum": 87,
    "WindSpeed": 2.3,
    "WindDir": 301
   },
   "noaa": {
    "Time": "2022-08-30T03:00:00Z",
    "Pressure": [
     1000,
     975,
     950,
     925,
     900,
     850,
     800,
     750,
     700,
     650,
     600,
     550,
     500,
     450,
     400,
     350,
     300,
     250,
     200,
     150,
     100,
     70,
     50,
     30,
     20,
     10,
     7,
     5,
     3,
     2,
     1
    ],
    "Height": [
     298,
     1028,
     1777,
     2542,
     3333,
     4989,
     6733,
     8564,
     10488,
     12511,
     14652,
     16930,
     19396,
     22094,
     25047,
     28314,
     31973,
     36134,
     41033,
     47025,
     55012,
     61871,
     68528,
     79031,
     87627,
     102711,
     110654,
     118350,
     130506,
     140390,
     157764
    ],
    "Temp": [
     26,
     24,
     23,
     24,
     27,
     27,
     24,
     19,
     14,
     8,
     1,
     -3,
     -4,
     -8,
     -14,
     -21,
     -30,
     -40,
     -49,
     -62,
     -72,
     -71,
     -63,
     -54,
     -50,
     -43,
     -38,
     -31,
     -21,
     -17,
     -8
    ],
    "Dew": [
     22,
     21,
     21,
     15,
     6,
     2,
     -2,
     -5,
     -5,
     -7,
     -7,
     -17,
     -37,
     -37,
     -40,
     -41,
     -47,
     -59,
     -62,
     -74,
     -82,
     -84,
     -87,
     -90,
     -91,
     9999,
     9999,
     9999,
     9999,
     9999,
     9999
    ],
    "WindDir": [
     187,
     347,
     340,
     190,
     49,
     101,
     138,
     157,
     164,
     180,
     220,
     210,
     162,
     120,
     96,
     95,
     102,
     150,
     165,
     146,
     144,
     103,
     92,
     100,
     92,
     103,
     89,
     87,
     109,
     74,
     76
    ],
    "WindSpeed": [
     2,
     3,
     3,
     4,
     5,
     7,
     9,
     10,
     6,
     4,
     7,
     8,
     10,
     13,
     13,
     16,
     18,
     18,
     14,
     13,
     19,
     19,
     22,
     35,
     38,
     33,
     35,
     40,
     28,
     29,
     38
    ]
   },
   "uwyo": null
  },
  "megido": {
   "ims": {
    "Time": "2022-08-30T03:00:00Z",
    "Temp": 24.6,
    "RelHum": 100,
    "WindSpeed": 1.5,
    "WindDir": 267
   },
   "noaa": {
    "Time": "2022-08-30T03:00:00Z",
    "Pressure": [
     1000,
     975,
     950,
     925,
     900,
     850,
     800,
     750,
     700,
     650,
     600,
     550,
     500,
     450,
     400,
     350,
     300,
     250,
     200,
     150,
     100,
     70,
     50,
     30,
     20,
     10,
     7,
     5,
     3,
     2,
     1
    ],
    "Height": [
     287,
     1021,
     1771,
     2537,
     3331,
     4991,
     6735,
     8564,
     10486,
     12511,
     14652,
     16928,
     19396,
     22096,
     25052,
     28323,
     31981,
     36136,
     41033,
     47028,
     55022,
     61889,
     68544,
     79046,
     87648,
     102739,
     110690,
     118379,
     130525,
     140426,
     157782
    ],
    "Temp": [
     26,
     25,
     23,
     24,
     28,
     27,
     24,
     19,
     13,
     7,
     1,
     -3,
     -3,
     -8,
     -14,
     -21,
     -30,
     -40,
     -49,
     -62,
     -72,
     -70,
     -63,
     -54,
     -50,
     -43,
     -39,
     -31,
     -21,
     -16,
     -9
    ],
    "Dew": [
     22,
     21,
     20,
     14,
     4,
     0,
     -1,
     -3,
     -5,
     -6,
     -8,
     -19,
     -38,
     -36,
     -41,
     -43,
     -42,
     -58,
     -64,
     -74,
     -82,
     -85,
     -87,
     -91,
     -93,
     9999,
     9999,
     9999,
     9999,
     9999,
     9999
    ],
    "WindDir": [
     298,
     326,
     334,
     172,
     204,
     82,
     168,
     174,
     181,
     200,
     209,
     213,
     178,
     135,
     99,
     98,
     109,
     155,
     182,
     158,
     142,
     107,
     94,
     101,
     90,
     105,
     86,
     89,
     106,
     75,
     78
    ],
    "WindSpeed": [
     3,
     6,
     6,
     7,
     6,
     4,
     9,
     12,
     10,
     8,
     8,
     11,
     11,
     11,
     9,
     12,
     16,
     18,
     14,
     12,
     16,
     17,
     24,
     34,
     36,
     34,
     35,
     40,
     30,
     27,
     40
    ]
   },
   "uwyo": null
  },
  "sde-teiman": {
   "ims": {
    "Time": "2022-08-30T03:00:00Z",
    "Temp": 23.5,
    "RelHum": 96,
    "WindSpeed": 2,
    "WindDir": 332
   },
   "noaa": {
    "Time": "2022-08-30T03:00:00Z",
    "Pressure": [
     1000,
     975,
     950,
     925,
     900,
     850,
     800,
     750,
     700,
     650,
     600,
     550,
     500,
     450,
     400,
     350,
     300,
     250,
     200,
     150,
     100,
     70,
     50,
     30,
     20,
     10,
     7,
     5,
     3,
     2,
     1
    ],
    "Height": [
     296,
     1031,
     1779,
     2543,
     3334,
     4989,
     6730,
     8561,
     10482,
     12506,
     14646,
     16922,
     19388,
     22084,
     25039,
     28308,
     31965,
     36124,
     41025,
     47017,
     54998,
     61853,
     68506,
     79007,
     87608,
     102671,
     110621,
     118339,
     130474,
     140362,
     157748
    ],
    "Temp": [
     26,
     24,
     23,
     24,
     27,
     26,
     23,
     19,
     13,
     7,
     1,
     -3,
     -4,
     -8,
     -14,
     -21,
     -30,
     -40,
     -49,
     -62,
     -72,
     -71,
     -63,
     -54,
     -50,
     -43,
     -37,
     -30,
     -21,
     -16,
     -8
    ],
    "Dew": [
     22,
     22,
     20,
     13,
     6,
     5,
     -1,
     -4,
     -5,
     -5,
     -6,
     -15,
     -40,
     -38,
     -40,
     -43,
     -50,
     -60,
     -63,
     -74,
     -81,
     -84,
     -88,
     -90,
     -92,
     9999,
     9999,
     9999,
     9999,
     9999,
     9999
    ],
    "WindDir": [
     348,
     350,
     178,
     23,
     46,
     97,
     137,
     140,
     138,
     152,
     211,
     216,
     147,
     120,
     101,
     93,
     105,
     145,
     154,
     136,
     141,
     97,
     93,
     99,
     91,
     99,
     89,
     92,
     107,
     72,
     73
    ],
    "WindSpeed": [
     5,
     6,
     6,
     6,
     7,
     6,
     10,
     13,
     9,
     7,
     9,
     10,
     11,
     17,
     17,
     17,
     19,
     17,
     15,
     14,
     22,
     19,
     24,
     36,
     38,
     36,
     35,
     37,
     30,
     27,
     36
    ]
   },
   "uwyo": null
  },
  "zefat": {
   "ims": {
    "Time": "2022-08-30T03:00:00Z",
    "Temp": 26.5,
    "RelHum": 32,
    "WindSpeed": 0.8,
    "WindDir": 347
   },
   "noaa": {
    "Time": "2022-08-30T03:00:00Z",
    "Pressure": [
     1000,
     975,
     950,
     925,
     900,
     850,
     800,
     750,
     700,
     650,
     600,
     550,
     500,
     450,
     400,
     350,
     300,
     250,
     200,
     150,
     100,
     70,
     50,
     30,
     20,
     10,
     7,
     5,
     3,
     2,
     1
    ],
    "Height": [
     286,
     1008,
     1763,
     2537,
     3336,
     4996,
     6738,
     8567,
     10488,
     12513,
     14652,
     16927,
     19402,
     22106,
     25058,
     28328,
     31989,
     36143,
     41037,
     47032,
     55034,
     61901,
     68565,
     79068,
     87676,
     102762,
     110729,
     118418,
     130546,
     140441,
     157806
    ],
    "Temp": [
     30,
     29,
     27,
     28,
     29,
     27,
     24,
     19,
     13,
     8,
     1,
     -3,
     -3,
     -8,
     -14,
     -21,
     -30,
     -40,
     -49,
     -62,
     -72,
     -70,
     -63,
     -54,
     -50,
     -42,
     -38,
     -30,
     -21,
     -16,
     -9
    ],
    "Dew": [
     16,
     15,
     14,
     10,
     5,
     -1,
     -1,
     -3,
     -6,
     -8,
     -8,
     -19,
     -39,
     -36,
     -41,
     -43,
     -43,
     -56,
     -66,
     -74,
     -82,
     -84,
     -87,
     -91,
     -93,
     9999,
     9999,
     9999,
     9999,
     9999,
     9999
    ],
    "WindDir": [
     159,
     159,
     142,
     80,
     58,
     73,
     176,
     185,
     201,
     208,
     212,
     232,
     194,
     155,
     103,
     95,
     113,
     150,
     192,
     165,
     149,
     107,
     92,
     100,
     91,
     103,
     87,
     88,
     101,
     74,
     77
    ],
    "WindSpeed": [
     1,
     2,
     1,
     1,
     4,
     7,
     6,
     8,
     11,
     10,
     12,
     12,
     9,
     8,
     7,
     10,
     14,
     15,
     14,
     12,
     13,
     17,
     23,
     33,
     34,
     36,
     34,
     39,
     31,
     26,
     40
    ]
   },
   "uwyo": null
  }
 },
 "4": {
  "bet-shaan": {
   "ims": {
    "Time": "2022-08-30T04:00:00Z",
    "Temp": 27.2,
    "RelHum": 87,
    "WindSpeed": 2,
    "WindDir": 306
   },
   "noaa": {
    "Time": "2022-08-30T04:00:00Z",
    "Pressure": [
     1000,
     975,
     950,
     925,
     900,
     850,
     800,
     750,
     700,
     650,
     600,
     550,
     500,
     450,
     400,
     350,
     300,
     250,
     200,
     150,
     100,
     70,
     50,
     30,
     20,
     10,
     7,
     5,
     3,
     2,
     1
    ],
    "Height": [
     303,
     1034,
     1784,
     2548,
     3339,
     4996,
     6739,
     8569,
     10492,
     12514,
     14655,
     16934,
     19399,
     22095,
     25047,
     28315,
     31973,
     36136,
     41036,
     47028,
     55021,
     61877,
     68532,
     79038,
     87633,
     102737,
     110678,
     118381,
     130500,
     140347,
     157724
    ],
    "Temp": [
     26,
     24,
     23,
     24,
     27,
     27,
     24,
     19,
     14,
     8,
     1,
     -3,
     -4,
     -8,
     -14,
     -21,
     -30,
     -40,
     -49,
     -62,
     -72,
     -71,
     -63,
     -54,
     -50,
     -43,
     -38,
     -31,
     -23,
     -17,
     -8
    ],
    "Dew": [
     22,
     21,
     21,
     15,
     6,
     2,
     -2,
     -5,
     -5,
     -7,
     -7,
     -18,
     -37,
     -37,
     -40,
     -41,
     -49,
     -60,
     -62,
     -74,
     -82,
     -84,
     -87,
     -90,
     -91,
     9999,
     9999,
     9999,
     9999,
     9999,
     9999
    ],
    "WindDir": [
     234,
     343,
     342,
     137,
     60,
     113,
     143,
     158,
     163,
     172,
     216,
     210,
     154,
     118,
     96,
     98,
     106,
     155,
     163,
     145,
     146,
     102,
     90,
     105,
     90,
     107,
     87,
     84,
     112,
     74,
     83
    ],
    "WindSpeed": [
     3,
     3,
     3,
     4,
     5,
     7,
     10,
     11,
     7,
     4,
     7,
     8,
     10,
     15,
     14,
     17,
     19,
     18,
     14,
     14,
     18,
     20,
     24,
     34,
     39,
     33,
     35,
     41,
     26,
     30,
     36
    ]
   },
   "uwyo": null
  },
  "megido": {
   "ims": {
    "Time": "2022-08-30T04:00:00Z",
    "Temp": 25.2,
    "RelHum": 98,
    "WindSpeed": 1.2,
    "WindDir": 267
   },
   "noaa": {
    "Time": "2022-08-30T04:00:00Z",
    "Pressure": [
     1000,
     975,
     950,
     925,
     900,
     850,
     800,
     750,
     700,
     650,
     600,
     550,
     500,
     450,
     400,
     350,
     300,
     250,
     200,
     150,
     100,
     70,
     50,
     30,
     20,
     10,
     7,
     5,
     3,
     2,
     1
    ],
    "Height": [
     293,
     1028,
     1778,
     2544,
     3338,
     4997,
     6740,
     8569,
     10490,
     12514,
     14655,
     16931,
     19399,
     22098,
     25053,
     28324,
     31982,
     36137,
     41036,
     47031,
     55031,
     61896,
     68546,
     79053,
     87656,
     102761,
     110714,
     118410,
     130524,
     140384,
     157737
    ],
    "Temp": [
     27,
     25,
     23,
     24,
     28,
     27,
     24,
     19,
     13,
     7,
     1,
     -3,
     -3,
     -8,
     -14,
     -21,
     -30,
     -40,
     -49,
     -62,
     -72,
     -70,
     -63,
     -54,
     -50,
     -43,
     -39,
     -31,
     -22,
     -17,
     -9
    ],
    "Dew": [
     22,
     21,
     20,
     15,
     5,
     0,
     -1,
     -3,
     -5,
     -6,
     -8,
     -19,
     -38,
     -36,
     -41,
     -43,
     -43,
     -59,
     -64,
     -74,
     -82,
     -85,
     -87,
     -91,
     -93,
     9999,
     9999,
     9999,
     9999,
     9999,
     9999
    ],
    "WindDir": [
     308,
     329,
     337,
     116,
     155,
     99,
     168,
     173,
     177,
     193,
     208,
     216,
     170,
     131,
     100,
     104,
     113,
     160,
     178,
     158,
     143,
     106,
     93,
     106,
     89,
     108,
     84,
     86,
     109,
     73,
     85
    ],
    "WindSpeed": [
     4,
     6,
     6,
     6,
     6,
     5,
     9,
     12,
     11,
     8,
     8,
     11,
     11,
     12,
     10,
     13,
     17,
     18,
     14,
     13,
     15,
     18,
     25,
     33,
     37,
     33,
     35,
     41,
     26,
     28,
     38
    ]
   },
   "uwyo": null
  },
  "sde-teiman": {
   "ims": {
    "Time": "2022-08-30T04:00:00Z",
    "Temp": 23.4,
    "RelHum": 97,
    "WindSpeed": 1.9,
    "WindDir": 330
   },
   "noaa": {
    "Time": "2022-08-30T04:00:00Z",
    "Pressure": [
     1000,
     975,
     950,
     925,
     900,
     850,
     800,
     750,
     700,
     650,
     600,
     550,
     500,
     450,
     400,
     350,
     300,
     250,
     200,
     150,
     100,
     70,
     50,
     30,
     20,
     10,
     7,
     5,
     3,
     2,
     1
    ],
    "Height": [
     303,
     1038,
     1786,
     2550,
     3340,
     4995,
     6735,
     8566,
     10486,
     12510,
     14650,
     16925,
     19389,
     22085,
     25039,
     28309,
     31965,
     36126,
     41027,
     47021,
     55004,
     61859,
     68513,
     79012,
     87616,
     102699,
     110645,
     118368,
     130467,
     140322,
     157713
    ],
    "Temp": [
     26,
     24,
     23,
     24,
     27,
     26,
     23,
     19,
     13,
     7,
     1,
     -3,
     -4,
     -8,
     -14,
     -21,
     -30,
     -40,
     -49,
     -62,
     -72,
     -71,
     -63,
     -54,
     -50,
     -43,
     -37,
     -30,
     -22,
     -16,
     -8
    ],
    "Dew": [
     22,
     22,
     20,
     14,
     6,
     5,
     -2,
     -4,
     -5,
     -5,
     -6,
     -16,
     -40,
     -38,
     -40,
     -43,
     -53,
     -61,
     -63,
     -74,
     -81,
     -84,
     -88,
     -90,
     -93,
     9999,
     9999,
     9999,
     9999,
     9999,
     9999
    ],
    "WindDir": [
     347,
     350,
     237,
     25,
     54,
     103,
     140,
     142,
     138,
     150,
     215,
     219,
     142,
     116,
     101,
     95,
     111,
     153,
     150,
     138,
     142,
     96,
     91,
     103,
     90,
     101,
     85,
     89,
     111,
     73,
     78
    ],
    "WindSpeed": [
     5,
     6,
     6,
     6,
     7,
     7,
     11,
     14,
     10,
     7,
     9,
     10,
     11,
     19,
     18,
     18,
     19,
     17,
     15,
     14,
     22,
     20,
     25,
     36,
     38,
     35,
     35,
     38,
     27,
     27,
     34
    ]
   },
   "uwyo": null
  },
  "zefat": {
   "ims": {
    "Time": "2022-08-30T04:00:00Z",
    "Temp": 26.4,
    "RelHum": 32,
    "WindSpeed": 0.9,
    "WindDir": 8
   },
   "noaa": {
    "Time": "2022-08-30T04:00:00Z",
    "Pressure": [
     1000,
     975,
     950,
     925,
     900,
     850,
     800,
     750,
     700,
     650,
     600,
     550,
     500,
     450,
     400,
     350,
     300,
     250,
     200,
     150,
     100,
     70,
     50,
     30,
     20,
     10,
     7,
     5,
     3,
     2,
     1
    ],
    "Height": [
     294,
     1016,
     1772,
     2546,
     3344,
     5003,
     6744,
     8572,
     10492,
     12517,
     14655,
     16930,
     19407,
     22109,
     25059,
     28328,
     31990,
     36144,
     41041,
     47033,
     55043,
     61906,
     68567,
     79072,
     87687,
     102778,
     110755,
     118456,
     130548,
     140402,
     157741
    ],
    "Temp": [
     30,
     29,
     27,
     28,
     28,
     27,
     24,
     19,
     13,
     8,
     1,
     -3,
     -3,
     -8,
     -14,
     -21,
     -30,
     -40,
     -49,
     -62,
     -72,
     -70,
     -63,
     -54,
     -50,
     -42,
     -38,
     -30,
     -22,
     -17,
     -8
    ],
    "Dew": [
     16,
     15,
     14,
     10,
     5,
     0,
     -1,
     -3,
     -6,
     -8,
     -8,
     -19,
     -39,
     -36,
     -41,
     -43,
     -43,
     -57,
     -65,
     -74,
     -82,
     -84,
     -87,
     -91,
     -93,
     9999,
     9999,
     9999,
     9999,
     9999,
     9999
    ],
    "WindDir": [
     152,
     152,
     139,
     82,
     70,
     87,
     162,
     175,
     196,
     207,
     219,
     237,
     187,
     150,
     105,
     101,
     117,
     155,
     192,
     162,
     149,
     106,
     92,
     104,
     91,
     107,
     86,
     87,
     102,
     71,
     84
    ],
    "WindSpeed": [
     1,
     2,
     1,
     1,
     4,
     8,
     7,
     8,
     11,
     9,
     11,
     12,
     9,
     9,
     8,
     11,
     15,
     16,
     14,
     13,
     12,
     18,
     24,
     32,
     35,
     37,
     34,
     39,
     28,
     27,
     39
    ]
   },
   "uwyo": null
  }
 },
 "5": {
  "bet-shaan": {
   "ims": {
    "Time": "2022-08-30T05:00:00Z",
    "Temp": 28.5,
    "RelHum": 79,
    "WindSpeed": 2.4,
    "WindDir": 323
   },
   "noaa": {
    "Time": "2022-08-30T05:00:00Z",
    "Pressure": [
     1000,
     975,
     950,
     925,
     900,
     850,
     800,
     750,
     700,
     650,
     600,
     550,
     500,
     450,
     400,
     350,
     300,
     250,
     200,
     150,
     100,
     70,
     50,
     30,
     20,
     10,
     7,
     5,
     3,
     2,
     1
    ],
    "Height": [
     308,
     1040,
     1790,
     2555,
     3346,
     5002,
     6745,
     8574,
     10496,
     12518,
     14658,
     16938,
     19402,
     22097,
     25048,
     28315,
     31972,
     36138,
     41039,
     47031,
     55030,
     61883,
     68536,
     79044,
     87638,
     102764,
     110703,
     118412,
     130494,
     140303,
     157684
    ],
    "Temp": [
     26,
     24,
     23,
     24,
     27,
     27,
     24,
     19,
     14,
     8,
     1,
     -3,
     -4,
     -8,
     -14,
     -21,
     -30,
     -40,
     -49,
     -62,
     -72,
     -71,
     -63,
     -54,
     -50,
     -43,
     -38,
     -31,
     -24,
     -17,
     -8
    ],
    "Dew": [
     22,
     21,
     21,
     15,
     6,
     2,
     -2,
     -5,
     -5,
     -7,
     -7,
     -18,
     -37,
     -37,
     -40,
     -41,
     -51,
     -61,
     -62,
     -74,
     -82,
     -84,
     -87,
     -90,
     -91,
     9999,
     9999,
     9999,
     9999,
     9999,
     9999
    ],
    "WindDir": [
     281,
     339,
     344,
     83,
     71,
     125,
     149,
     159,
     161,
     164,
     212,
     211,
     147,
     116,
     97,
     101,
     110,
     161,
     162,
     144,
     148,
     101,
     87,
     110,
     88,
     110,
     84,
     82,
     115,
     73,
     90
    ],
    "WindSpeed": [
     3,
     4,
     3,
     4,
     5,
     7,
     11,
     12,
     8,
     4,
     6,
     8,
     10,
     16,
     15,
     18,
     20,
     18,
     14,
     14,
     17,
     21,
     26,
     33,
     40,
     32,
     35,
     42,
     23,
     31,
     33
    ]
   },
   "uwyo": null
  },
  "megido": {
   "ims": {
    "Time": "2022-08-30T05:00:00Z",
    "Temp": 27.2,
    "RelHum": 86,
    "WindSpeed": 1.7,
    "WindDir": 292
   },
   "noaa": {
    "Time": "2022-08-30T05:00:00Z",
    "Pressure": [
     1000,
     975,
     950,
     925,
     900,
     850,
     800,
     750,
     700,
     650,
     600,
     550,
     500,
     450,
     400,
     350,
     300,
     250,
     200,
     150,
     100,
     70,
     50,
     30,
     20,
     10,
     7,
     5,
     3,
     2,
     1
    ],
    "Height": [
     299,
     1035,
     1786,
     2551,
     3345,
     5003,
     6745,
     8574,
     10494,
     12518,
     14658,
     16934,
     19402,
     22100,
     25054,
     28325,
     31983,
     36139,
     41039,
     47034,
     55040,
     61902,
     68547,
     79060,
     87664,
     102783,
     110739,
     118442,
     130523,
     140341,
     157692
    ],
    "Temp": [
     27,
     25,
     23,
     24,
     28,
     27,
     24,
     19,
     13,
     7,
     1,
     -3,
     -3,
     -8,
     -14,
     -21,
     -30,
     -40,
     -49,
     -62,
     -72,
     -70,
     -63,
     -54,
     -50,
     -43,
     -39,
     -31,
     -23,
     -17,
     -9
    ],
    "Dew": [
     22,
     21,
     20,
     15,
     5,
     0,
     -1,
     -3,
     -5,
     -6,
     -8,
     -19,
     -38,
     -36,
     -41,
     -43,
     -43,
     -60,
     -64,
     -74,
     -82,
     -85,
     -87,
     -91,
     -93,
     9999,
     9999,
     9999,
     9999,
     9999,
     9999
    ],
    "WindDir": [
     318,
     332,
     340,
     60,
     106,
     116,
     167,
     173,
     173,
     187,
     207,
     220,
     162,
     127,
     102,
     110,
     116,
     166,
     175,
     158,
     144,
     104,
     91,
     111,
     87,
     112,
     82,
     83,
     112,
     71,
     93
    ],
    "WindSpeed": [
     4,
     6,
     6,
     6,
     5,
     5,
     9,
     13,
     11,
     8,
     7,
     11,
     11,
     13,
     11,
     14,
     18,
     18,
     14,
     14,
     14,
     18,
     27,
     32,
     38,
     33,
     35,
     42,
     23,
     30,
     36
    ]
   },
   "uwyo": null
  },
  "sde-teiman": {
   "ims": {
    "Time": "2022-08-30T05:00:00Z",
    "Temp": 24.4,
    "RelHum": 91,
    "WindSpeed": 2.2,
    "WindDir": 336
   },
   "noaa": {
    "Time": "2022-08-30T05:00:00Z",
    "Pressure": [
     1000,
     975,
     950,
     925,
     900,
     850,
     800,
     750,
     700,
     650,
     600,
     550,
     500,
     450,
     400,
     350,
     300,
     250,
     200,
     150,
     100,
     70,
     50,
     30,
     20,
     10,
     7,
     5,
     3,
     2,
     1
    ],
    "Height": [
     310,
     1045,
     1793,
     2557,
     3346,
     5000,
     6740,
     8571,
     10490,
     12514,
     14654,
     16928,
     19391,
     22085,
     25039,
     28309,
     31965,
     36128,
     41030,
     47025,
     55010,
     61864,
     68519,
     79017,
     87625,
     102727,
     110670,
     118396,
     130460,
     140282,
     157679
    ],
    "Temp": [
     26,
     24,
     23,
     24,
     27,
     26,
     23,
     19,
     13,
     7,
     1,
     -3,
     -4,
     -8,
     -14,
     -21,
     -30,
     -40,
     -49,
     -62,
     -72,
     -71,
     -63,
     -54,
     -50,
     -43,
     -37,
     -30,
     -23,
     -16,
     -8
    ],
    "Dew": [
     22,
     22,
     20,
     14,
     6,
     5,
     -2,
     -4,
     -5,
     -5,
     -6,
     -16,
     -40,
     -38,
     -40,
     -43,
     -56,
     -62,
     -63,
     -74,
     -81,
     -84,
     -88,
     -90,
     -93,
     9999,
     9999,
     9999,
     9999,
     9999,
     9999
    ],
    "WindDir": [
     346,
     350,
     296,
     28,
     63,
     109,
     143,
     144,
     138,
     148,
     219,
     221,
     137,
     113,
     101,
     97,
     117,
     161,
     146,
     140,
     143,
     94,
     89,
     106,
     88,
     103,
     81,
     87,
     114,
     74,
     83
    ],
    "WindSpeed": [
     5,
     6,
     6,
     6,
     7,
     8,
     12,
     15,
     10,
     7,
     9,
     10,
     11,
     21,
     20,
     19,
     19,
     17,
     15,
     14,
     22,
     21,
     27,
     36,
     38,
     34,
     35,
     39,
     25,
     27,
     32
    ]
   },
   "uwyo": null
  },
  "zefat": {
   "ims": {
    "Time": "2022-08-30T05:00:00Z",
    "Temp": 26.9,
    "RelHum": 31,
    "WindSpeed": 0.6,
    "WindDir": 60
   },
   "noaa": {
    "Time": "2022-08-30T05:00:00Z",
    "Pressure": [
     1000,
     975,
     950,
     925,
     900,
     850,
     800,
     750,
     700,
     650,
     600,
     550,
     500,
     450,
     400,
     350,
     300,
     250,
     200,
     150,
     100,
     70,
     50,
     30,
     20,
     10,
     7,
     5,
     3,
     2,
     1
    ],
    "Height": [
     302,
     1024,
     1781,
     2555,
     3353,
     5009,
     6749,
     8577,
     10496,
     12521,
     14658,
     16934,
     19411,
     22112,
     25060,
     28329,
     31992,
     36146,
     41045,
     47035,
     55052,
     61911,
     68569,
     79076,
     87698,
     102794,
     110781,
     118494,
     130551,
     140363,
     157676
    ],
    "Temp": [
     30,
     29,
     27,
     28,
     28,
     27,
     24,
     19,
     13,
     8,
     1,
     -3,
     -3,
     -8,
     -14,
     -21,
     -30,
     -40,
     -49,
     -62,
     -72,
     -70,
     -63,
     -54,
     -50,
     -42,
     -37,
     -30,
     -23,
     -18,
     -8
    ],
    "Dew": [
     16,
     15,
     14,
     10,
     5,
     0,
     -1,
     -3,
     -6,
     -8,
     -8,
     -18,
     -39,
     -36,
     -41,
     -43,
     -43,
     -59,
     -64,
     -74,
     -82,
     -84,
     -87,
     -91,
     -94,
     9999,
     9999,
     9999,
     9999,
     9999,
     9999
    ],
    "WindDir": [
     145,
     145,
     136,
     84,
     82,
     100,
     148,
     165,
     190,
     206,
     227,
     242,
     180,
     145,
     107,
     107,
     121,
     160,
     192,
     159,
     148,
     105,
     93,
     107,
     91,
     110,
     84,
     85,
     103,
     68,
     91
    ],
    "WindSpeed": [
     1,
     2,
     1,
     1,
     5,
     9,
     9,
     8,
     11,
     9,
     10,
     12,
     9,
     10,
     9,
     12,
     16,
     16,
     14,
     14,
     11,
     18,
     25,
     32,
     36,
     38,
     34,
     39,
     25,
     28,
     38
    ]
   },
   "uwyo": null
  }
 },
 "6": {
  "bet-shaan": {
   "ims": {
    "Time": "2022-08-30T06:00:00Z",
    "Temp": 30.2,
    "RelHum": 70,
    "WindSpeed": 2.3,
    "WindDir": 332
   },
   "noaa": {
    "Time": "2022-08-30T06:00:00Z",
    "Pressure": [
     1000,
     975,
     950,
     925,
     900,
     850,
     800,
     750,
     700,
     650,
     600,
     550,
     500,
     450,
     400,
     350,
     300,
     250,
     200,
     150,
     100,
     70,
     50,
     30,
     20,
     10,
     7,
     5,
     3,
     2,
     1
    ],
    "Height": [
     314,
     1046,
     1797,
     2562,
     3353,
     5009,
     6751,
     8579,
     10501,
     12522,
     14662,
     16942,
     19406,
     22099,
     25049,
     28316,
     31971,
     36141,
     41043,
     47034,
     55039,
     61889,
     68540,
     79051,
     87644,
     102791,
     110728,
     118444,
     130488,
     140259,
     157644
    ],
    "Temp": [
     27,
     25,
     23,
     24,
     27,
     26,
     23,
     18,
     13,
     7,
     1,
     -3,
     -4,
     -9,
     -15,
     -21,
     -30,
     -39,
     -49,
     -62,
     -71,
     -71,
     -64,
     -54,
     -50,
     -43,
     -38,
     -30,
     -26,
     -18,
     -8
    ],
    "Dew": [
     21,
     21,
     20,
     14,
     7,
     3,
     -3,
     -5,
     -6,
     -7,
     -7,
     -19,
     -36,
     -37,
     -40,
     -40,
     -54,
     -63,
     -63,
     -75,
     -81,
     -84,
     -87,
     -90,
     -91,
     9999,
     9999,
     9999,
     9999,
     9999,
     9999
    ],
    "WindDir": [
     329,
     334,
     346,
     29,
     83,
     137,
     155,
     160,
     159,
     156,
     208,
     212,
     139,
     114,
     98,
     105,
     114,
     167,
     160,
     142,
     150,
     99,
     84,
     115,
     86,
     114,
     81,
     79,
     118,
     72,
     97
    ],
    "WindSpeed": [
     4,
     5,
     4,
     3,
     4,
     8,
     13,
     14,
     9,
     5,
     5,
     9,
     11,
     18,
     16,
     20,
     21,
     19,
     13,
     15,
     16,
     22,
     28,
     32,
     42,
     31,
     34,
     43,
     20,
     32,
     30
    ]
   },
   "uwyo": null
  },
  "megido": {
   "ims": {
    "Time": "2022-08-30T06:00:00Z",
    "Temp": 29.2,
    "RelHum": 74,
    "WindSpeed": 1.7,
    "WindDir": 292
   },
   "noaa": {
    "Time": "2022-08-30T06:00:00Z",
    "Pressure": [
     1000,
     975,
     950,
     925,
     900,
     850,
     800,
     750,
     700,
     650,
     600,
     550,
     500,
     450,
     400,
     350,
     300,
     250,
     200,
     150,
     100,
     70,
     50,
     30,
     20,
     10,
     7,
     5,
     3,
     2,
     1
    ],
    "Height": [
     305,
     1043,
     1794,
     2559,
     3353,
     5009,
     6751,
     8579,
     10498,
     12522,
     14662,
     16938,
     19406,
     22103,
     25055,
     28326,
     31984,
     36141,
     41043,
     47037,
     55049,
     61909,
     68549,
     79068,
     87673,
     102805,
     110764,
     118474,
     130521,
     140298,
     157647
    ],
    "Temp": [
     28,
     26,
     23,
     23,
     28,
     27,
     23,
     18,
     13,
     7,
     1,
     -2,
     -4,
     -9,
     -14,
     -21,
     -30,
     -39,
     -49,
     -62,
     -71,
     -71,
     -64,
     -53,
     -51,
     -42,
     -38,
     -30,
     -25,
     -18,
     -8
    ],
    "Dew": [
     21,
     20,
     20,
     16,
     6,
     1,
     0,
     -4,
     -6,
     -6,
     -7,
     -18,
     -37,
     -37,
     -42,
     -43,
     -44,
     -62,
     -63,
     -74,
     -81,
     -84,
     -87,
     -91,
     -92,
     9999,
     9999,
     9999,
     9999,
     9999,
     9999
    ],
    "WindDir": [
     328,
     336,
     344,
     4,
     57,
     134,
     166,
     172,
     168,
     180,
     206,
     224,
     154,
     123,
     104,
     116,
     120,
     172,
     171,
     159,
     145,
     102,
     89,
     116,
     85,
     116,
     80,
     79,
     115,
     69,
     101
    ],
    "WindSpeed": [
     5,
     5,
     5,
     5,
     4,
     6,
     10,
     14,
     12,
     7,
     6,
     11,
     10,
     15,
     13,
     15,
     20,
     19,
     13,
     15,
     13,
     19,
     29,
     31,
     40,
     32,
     34,
     43,
     19,
     32,
     33
    ]
   },
   "uwyo": null
  },
  "sde-teiman": {
   "ims": {
    "Time": "2022-08-30T06:00:00Z",
    "Temp": 26.2,
    "RelHum": 80,
    "WindSpeed": 1.8,
    "WindDir": 334
   },
   "noaa": {
    "Time": "2022-08-30T06:00:00Z",
    "Pressure": [
     1000,
     975,
     950,
     925,
     900,
     850,
     800,
     750,
     700,
     650,
     600,
     550,
     500,
     450,
     400,
     350,
     300,
     250,
     200,
     150,
     100,
     70,
     50,
     30,
     20,
     10,
     7,
     5,
     3,
     2,
     1
    ],
    "Height": [
     318,
     1053,
     1801,
     2565,
     3353,
     5006,
     6745,
     8576,
     10495,
     12519,
     14658,
     16932,
     19393,
     22086,
     25039,
     28310,
     31965,
     36131,
     41033,
     47030,
     55016,
     61870,
     68526,
     79022,
     87634,
     102755,
     110695,
     118425,
     130452,
     140242,
     157644
    ],
    "Temp": [
     27,
     25,
     23,
     23,
     26,
     26,
     23,
     19,
     13,
     7,
     1,
     -3,
     -5,
     -9,
     -14,
     -21,
     -30,
     -39,
     -49,
     -62,
     -72,
     -70,
     -64,
     -54,
     -49,
     -43,
     -37,
     -30,
     -25,
     -17,
     -9
    ],
    "Dew": [
     21,
     21,
     20,
     15,
     7,
     4,
     -3,
     -5,
     -5,
     -6,
     -7,
     -17,
     -39,
     -39,
     -41,
     -44,
     -59,
     -63,
     -63,
     -75,
     -81,
     -84,
     -87,
     -90,
     -94,
     9999,
     9999,
     9999,
     9999,
     9999,
     9999
    ],
    "WindDir": [
     345,
     349,
     356,
     31,
     72,
     115,
     147,
     146,
     137,
     146,
     223,
     224,
     131,
     109,
     100,
     99,
     124,
     170,
     142,
     142,
     145,
     92,
     87,
     110,
     86,
     106,
     77,
     84,
     118,
     75,
     89
    ],
    "WindSpeed": [
     5,
     5,
     5,
     5,
     8,
     9,
     13,
     17,
     11,
     8,
     10,
     9,
     11,
     23,
     22,
     21,
     19,
     16,
     14,
     13,
     21,
     22,
     29,
     35,
     39,
     33,
     34,
     41,
     22,
     28,
     29
    ]
   },
   "uwyo": null
  },
  "zefat": {
   "ims": {
    "Time": "2022-08-30T06:00:00Z",
    "Temp": 27.8,
    "RelHum": 29,
    "WindSpeed": 0.9,
    "WindDir": 87
   },
   "noaa": {
    "Time": "2022-08-30T06:00:00Z",
    "Pressure": [
     1000,
     975,
     950,
     925,
     900,
     850,
     800,
     750,
     700,
     650,
     600,
     550,
     500,
     450,
     400,
     350,
     300,
     250,
     200,
     150,
     100,
     70,
     50,
     30,
     20,
     10,
     7,
     5,
     3,
     2,
     1
    ],
    "Height": [
     311,
     1033,
     1791,
     2565,
     3362,
     5016,
     6755,
     8582,
     10501,
     12526,
     14662,
     16938,
     19416,
     22116,
     25062,
     28330,
     31994,
     36148,
     41049,
     47037,
     55062,
     61916,
     68572,
     79081,
     87709,
     102811,
     110807,
     118533,
     130554,
     140324,
     157611
    ],
    "Temp": [
     31,
     30,
     28,
     27,
     27,
     26,
     23,
     18,
     13,
     7,
     1,
     -2,
     -3,
     -9,
     -15,
     -21,
     -30,
     -40,
     -49,
     -62,
     -71,
     -71,
     -64,
     -53,
     -50,
     -42,
     -36,
     -31,
     -24,
     -19,
     -7
    ],
    "Dew": [
     17,
     16,
     15,
     9,
     5,
     1,
     0,
     -2,
     -5,
     -7,
     -7,
     -17,
     -38,
     -37,
     -40,
     -43,
     -44,
     -61,
     -63,
     -74,
     -81,
     -84,
     -87,
     -91,
     -95,
     9999,
     9999,
     9999,
     9999,
     9999,
     9999
    ],
    "WindDir": [
     138,
     138,
     133,
     87,
     94,
     114,
     133,
     155,
     184,
     205,
     235,
     247,
     172,
     139,
     110,
     114,
     125,
     166,
     193,
     156,
     147,
     103,
     94,
     111,
     90,
     114,
     82,
     83,
     105,
     65,
     98
    ],
    "WindSpeed": [
     2,
     3,
     2,
     2,
     6,
     11,
     11,
     9,
     10,
     8,
     8,
     11,
     8,
     11,
     10,
     13,
     17,
     17,
     14,
     15,
     10,
     19,
     27,
     31,
     37,
     39,
     33,
     38,
     22,
     29,
     37
    ]
   },
   "uwyo": null
  }
 },
 "7": {
  "bet-shaan": {
   "ims": {
    "Time": "2022-08-30T07:00:00Z",
    "Temp": 32.2,
    "RelHum": 61,
    "WindSpeed": 1.8,
    "WindDir": 337
   },
   "noaa": null,
   "uwyo": null
  },
  "megido": {
   "ims": {
    "Time": "2022-08-30T07:00:00Z",
    "Temp": 31.7,
    "RelHum": 61,
    "WindSpeed": 1.7,
    "WindDir": 289
   },
   "noaa": null,
   "uwyo": null
  },
  "sde-teiman": {
   "ims": {
    "Time": "2022-08-30T07:00:00Z",
    "Temp": 28.7,
    "RelHum": 64,
    "WindSpeed": 1.8,
    "WindDir": 323
   },
   "noaa": null,
   "uwyo": null
  },
  "zefat": {
   "ims": {
    "Time": "2022-08-30T07:00:00Z",
    "Temp": 28.8,
    "RelHum": 27,
    "WindSpeed": 0.8,
    "WindDir": 140
   },
   "noaa": null,
   "uwyo": null
  }
 },
 "8": {
  "bet-shaan": {
   "ims": {
    "Time": "2022-08-30T08:00:00Z",
    "Temp": 34.2,
    "RelHum": 51,
    "WindSpeed": 1.4,
    "WindDir": 345
   },
   "noaa": null,
   "uwyo": null
  },
  "megido": {
   "ims": {
    "Time": "2022-08-30T08:00:00Z",
    "Temp": 33.9,
    "RelHum": 51,
    "WindSpeed": 1.7,
    "WindDir": 286
   },
   "noaa": null,
   "uwyo": null
  },
  "sde-teiman": {
   "ims": {
    "Time": "2022-08-30T08:00:00Z",
    "Temp": 31.3,
    "RelHum": 52,
    "WindSpeed": 2,
    "WindDir": 316
   },
   "noaa": null,
   "uwyo": null
  },
  "zefat": {
   "ims": {
    "Time": "2022-08-30T08:00:00Z",
    "Temp": 29.6,
    "RelHum": 27,
    "WindSpeed": 1.7,
    "WindDir": 191
   },
   "noaa": null,
   "uwyo": null
  }
 },
 "9": {
  "bet-shaan": {
   "ims": {
    "Time": "2022-08-30T09:00:00Z",
    "Temp": 36.5,
    "RelHum": 42,
    "WindSpeed": 1.3,
    "WindDir": 342
   },
   "noaa": null,
   "uwyo": null
  },
  "megido": {
   "ims": {
    "Time": "2022-08-30T09:00:00Z",
    "Temp": 35.5,
    "RelHum": 45,
    "WindSpeed": 2,
    "WindDir": 289
   },
   "noaa": null,
   "uwyo": null
  },
  "sde-teiman": {
   "ims": {
    "Time": "2022-08-30T09:00:00Z",
    "Temp": 33.5,
    "RelHum": 45,
    "WindSpeed": 2.2,
    "WindDir": 305
   },
   "noaa": null,
   "uwyo": null
  },
  "zefat": {
   "ims": {
    "Time": "2022-08-30T09:00:00Z",
    "Temp": 30.5,
    "RelHum": 25,
    "WindSpeed": 2.4,
    "WindDir": 197
   },
   "noaa": null,
   "uwyo": null
  }
 }
}
